Workbook

Sheet Léame
B2: Modelo de datos · TRIM Hidrocarburos
B3: Las tablas que guarda el backend y cómo se relacionan (PostgreSQL 16)
B5: CÓMO SE LEE
B6: Tablas | C6: Una fila por tabla: su grupo, para qué sirve, el tipo TypeScript del front que guarda, quién la escribe, qué endpoint la lee y sus reglas. «Columnas» y «Relaciones que salen» se cuentan con fórmulas sobre las otras hojas.
B7: Columnas | C7: Una fila por columna: tipo PostgreSQL, si admite nulo, clave primaria (PK), clave foránea (FK: tabla.columna a la que apunta), único, restricción CHECK, descripción y un valor de ejemplo del demo. Use el filtro de la cabecera para ver una tabla.
B8: Relaciones | C8: Cada clave foránea dicha en palabras: de qué columna a qué columna, su cardinalidad (N:1 = muchas filas de la primera apuntan a una de la segunda) y qué significa.
B9: Filas de ejemplo | C9: Filas reales del demo (ids, fechas y valores de referencia/insumos), tabla por tabla. No son datos de un cliente.
B10: Diagrama | C10: El diagrama entidad-relación de cada grupo, el mismo del capítulo 3 del documento.
B11: Fuente de verdad | C11: El archivo que se ejecuta es esquema.sql (docs/backend/). Este libro se genera desde la misma especificación y se comprobó que coincide tabla por tabla y columna por columna.
B13: GRUPOS
B14: Registro de campos y planta | C14: Quién es cada campo, qué activos tiene (equipos de superficie y pozos) y la topología de su planta. Un cliente nuevo son filas aquí, no código.
B15: Cadena de datos | C15: Del gateway del borde al tag: se llena sola con el nacimiento de Sparkplug B (NBIRTH/DBIRTH). Da la procedencia de cada número y la banda normal versionada de cada tag.
B16: Series | C16: La lectura de cada tag en el tiempo (tag, instante, valor, calidad), particionada por mes; opcionalmente hipertabla de TimescaleDB.
B17: Insumos del motor | C17: Lo que el borde entrega y el motor consume (interfaz Insumos): pozos y pruebas, eventos de los controladores, paradas de bombas, caídas de servicios, fiscal diario, metrología, perfiles de bomba, límites y alarmas, y el catálogo de daños de ISO 14224.
B18: Configuración firmada | C18: Lo único técnico que entra a mano: metas, precio, regla de cierre, perfil, tanques, respaldos, programa y membrete. Cada firma es una versión completa e inmutable.
B19: Personas | C19: Roles y capacidades del producto, usuarios con sus campos y su WhatsApp, la identidad del SSO y el rastro de cambios de acceso.
B20: Lo que entra a mano y WhatsApp | C20: Respuestas de los operarios, análisis de confiabilidad, informes con folio, el registro de WhatsApp (saliente y entrante), predicciones del vigía, la asignación oficial cargada y los cambios de planta.
B21: Lo que se lee de SAP PM | C21: Espejo de lo que TRIM necesita de SAP: identidad del equipo, avisos, órdenes con sus horas y repuestos, y stock. TRIM no crea órdenes.
B22: Precálculo de meses cerrados | C22: Caché verificable del motor para meses cerrados y publicados: libro del mes por campo, factor de asignación, tramos por día y asignación por pozo.
B24: TOTALES
B25: Tablas | C25: =COUNTA(Tablas!B:B)-1
B26: Columnas | C26: =COUNTA(Columnas!B:B)-1
B27: Relaciones | C27: =COUNTA(Relaciones!A:A)-1

Sheet Tablas
A1: Grupo | B1: Tabla | C1: Para qué sirve | D1: Tipo TS (front) | E1: Quién la escribe | F1: Endpoints que la leen o escriben | G1: Reglas | H1: Columnas | I1: Relaciones que salen
A2: Registro de campos y planta | B2: campo | C2: Registro de campos de la empresa (tipo Campo, src/entities/tipos.ts). GET /api/campos. Un cliente nuevo son filas aquí, no código. Las metas, el perfil y el precio NO viven aquí: son configuración firmada. | D2: Campo (src/entities/tipos.ts) | E2: Implementación (alta de un cliente o de un campo); no hay endpoint de escritura. | F2: GET /api/campos | G2: El catálogo no puede traer un campo que no esté aquí (el arranque se detiene). La configuración firmada solo acepta campos del registro (validarConfig, 422). | H2: =COUNTIF(Columnas!$B:$B,B2) | I2: =COUNTIF(Relaciones!$A:$A,B2)
A3: Registro de campos y planta | B3: activo | C3: Supertipo: todo lo que tiene código en un campo. clase=catalogo es un equipo de superficie (tabla equipo); clase=pozo es un pozo (tabla pozo). Corresponde a ClaseEquipo de src/entities/equipo-vivo.ts. Un mismo código existe en varios campos (P-201B): la identidad es (campo, código). | D3: ClaseEquipo (src/entities/equipo-vivo.ts) | E3: Servidor, al dar de alta un equipo o un pozo. | F3: (interna: destino de las FK a «equipo o pozo») | G3: Un código es único en su campo; el mismo código existe en varios campos (P-201B). Único: (campo_id, codigo, clase). | H3: =COUNTIF(Columnas!$B:$B,B3) | I3: =COUNTIF(Relaciones!$A:$A,B3)
A4: Registro de campos y planta | B4: equipo | C4: Registro de ingeniería: un equipo de superficie en un campo (la parte estática de Equipo/EquipoEnCampo, src/entities/tipos.ts y equipos.ts). Lo declara el cliente una vez. Sale en GET /api/catalogo → campos[c].registroEquipos y en el inventario de Conectores. Lo vivo (marcha, estado, severidad, lecturas) NO se guarda aquí: lo calcula el servidor. | D4: Equipo / EquipoEnCampo, parte estática (src/entities/tipos.ts, equipos.ts) | E4: Ingeniería del cliente, una vez por campo (registro de ingeniería). | F4: GET /api/catalogo → campos[c].registroEquipos GET /api/campos/:campo/inventario → equipos GET /api/vistas/equipos… | G4: servicio dice qué tipo de causa se carga cuando cae (aire, energia…); la regla no depende del id. equipo.fiscal de la API sale de punto_medicion. aguas_abajo y redundancia son del registro del campo; en una bomba de la línea van NULL y la API los arma del respaldo firmado (respaldoEnCampo). | H4: =COUNTIF(Columnas!$B:$B,B4) | I4: =COUNTIF(Relaciones!$A:$A,B4)
A5: Registro de campos y planta | B5: planta_campo | C5: Cabecera del esquema de planta de un campo: caudales de diseño y los cuatro cuellos de botella (Caudales y Chokes de PlantaCampo, src/entities/planta.ts). Sale en GET /api/catalogo → campos[c].planta. Un campo sin fila aquí no trae planta (hueco), nunca la de otro. | D5: PlantaCampo: caudales, chokes, nota (src/entities/planta.ts) | E5: Implementación; los cambios de trenes y miembros por POST /api/planta/cambios (conector:configurar). | F5: GET /api/catalogo → campos[c].planta | G5: Un campo sin planta no trae planta (hueco), nunca la de otro. | H5: =COUNTIF(Columnas!$B:$B,B5) | I5: =COUNTIF(Relaciones!$A:$A,B5)
A6: Registro de campos y planta | B6: planta_elemento | C6: Un elemento de un tren del esquema de planta (Elemento, src/entities/planta.ts). Cambia solo con POST /api/planta/cambios (agregar-elemento, quitar-elemento), que registra cambio_planta. | D6: Elemento (src/entities/planta.ts) | E6: Servidor al aplicar aplicarCambioPlanta (administrador, conector:configurar). | F6: GET /api/catalogo → campos[c].planta POST /api/planta/cambios (agregar-elemento, quitar-elemento) | G6: Un id no se repite entre elementos y miembros del campo (409/422). Único: (campo_id, tren, orden). Un id no se repite entre elementos y miembros del campo. [trigger planta_elemento_id_unico: INSERT UPDATE] | H6: =COUNTIF(Columnas!$B:$B,B6) | I6: =COUNTIF(Relaciones!$A:$A,B6)
A7: Registro de campos y planta | B7: planta_miembro | C7: Miembro de un elemento con varios del mismo tipo (pozos, tanques en especificación): Miembro de src/entities/planta.ts. Cambia con agregar-miembro / quitar-miembro. | D7: Miembro (src/entities/planta.ts) | E7: Servidor al aplicar aplicarCambioPlanta. | F7: GET /api/catalogo → campos[c].planta POST /api/planta/cambios (agregar-miembro, quitar-miembro) | G7: El grupo tiene que existir y admitir miembros (422 «Ese conjunto no existe»). Único: (campo_id, elemento_id, orden). Un id no se repite entre elementos y miembros del campo. [trigger planta_miembro_id_unico: INSERT UPDATE] | H7: =COUNTIF(Columnas!$B:$B,B7) | I7: =COUNTIF(Relaciones!$A:$A,B7)
A8: Cadena de datos | B8: gateway | C8: Gateway del borde (nodo de Sparkplug B): se crea solo al recibir su NBIRTH. Es del campo donde se inscribió; si se presenta con otro, el nacimiento se rechaza (403 gateway-de-otro-campo, tabla rechazo). GET /api/campos/:campo/inventario y bloque tecnico de la procedencia. | E8: Borde (NBIRTH), autenticado por certificado de cliente. | F8: POST /api/ingesta/nacimiento GET /api/campos/:campo/inventario GET …/tags/:tag/procedencia → tecnico | G8: Un gateway inscrito en un campo que se presenta con otro: 403 gateway-de-otro-campo y fila en rechazo. Único: (id, campo_id). | H8: =COUNTIF(Columnas!$B:$B,B8) | I8: =COUNTIF(Relaciones!$A:$A,B8)
A9: Cadena de datos | B9: inscripcion | C9: Código de un solo uso con que un gateway nuevo se inscribe en un campo (POST /api/inscripcion, capacidad conector:configurar). En producción se canjea por el certificado de cliente en el primer contacto. Se guarda la huella del código, nunca el código. | E9: Persona con conector:configurar y el campo asignado; el borde la canjea. | F9: POST /api/inscripcion | G9: Un solo uso; vence a las 24 h. Se guarda la huella del código, nunca el código. Único: (codigo_huella). | H9: =COUNTIF(Columnas!$B:$B,B9) | I9: =COUNTIF(Relaciones!$A:$A,B9)
A10: Cadena de datos | B10: nacimiento | C10: Bitácora de nacimientos aceptados (NBIRTH + DBIRTH; POST /api/ingesta/nacimiento → { gateway, tags, pendientes }). Solo inserción: cada reconexión de Sparkplug es una fila. | E10: Borde. | F10: POST /api/ingesta/nacimiento | G10: Todo o nada: con una falta, 400 con faltas[] y nada escrito. Solo inserción. Solo inserción: UPDATE, DELETE y TRUNCATE rechazados (SQLSTATE 23001). [trigger nacimiento_sin_truncate: TRUNCATE] Solo inserción: UPDATE, DELETE y TRUNCATE rechazados (SQLSTATE 23001). [trigger nacimiento_solo_insercion: UPDATE DELETE] | H10: =COUNTIF(Columnas!$B:$B,B10) | I10: =COUNTIF(Relaciones!$A:$A,B10)
A11: Cadena de datos | B11: rechazo | C11: Nacimientos rechazados: un borde que se presenta con otro campo o declara tags de otro gateway es un hecho de seguridad y queda escrito (fuera de la transacción del nacimiento, que se deshizo). Solo inserción. Sin FK: el gateway o el campo pueden no existir. | E11: Servidor, fuera de la transacción del nacimiento rechazado. | F11: POST /api/ingesta/nacimiento (403/409) | G11: Solo inserción. Solo inserción: UPDATE, DELETE y TRUNCATE rechazados (SQLSTATE 23001). [trigger rechazo_sin_truncate: TRUNCATE] Solo inserción: UPDATE, DELETE y TRUNCATE rechazados (SQLSTATE 23001). [trigger rechazo_solo_insercion: UPDATE DELETE] | H11: =COUNTIF(Columnas!$B:$B,B11) | I11: =COUNTIF(Relaciones!$A:$A,B11)
A12: Cadena de datos | B12: fuente | C12: Conector del borde hacia una fuente de datos del campo (un historiador PI, un servidor OPC UA, un PLC por Modbus, el computador de flujo por ROC Plus…). Sale de dispositivos[].fuente del nacimiento. El simulador junta fuente y dispositivo en una sola fila (id gateway:protocolo:dispositivo); aquí se separan. | E12: Borde (dispositivos[].fuente del DBIRTH). | F12: GET …/tags/:tag/procedencia → lectura.protocolo, tecnico.endpoint | G12: Siempre solo-lectura: TRIM no escribe en el PLC. Único: (gateway_id, protocolo, endpoint). Único: (id, gateway_id, campo_id). | H12: =COUNTIF(Columnas!$B:$B,B12) | I12: =COUNTIF(Relaciones!$A:$A,B12)
A13: Cadena de datos | B13: dispositivo | C13: Dispositivo de Sparkplug B declarado en un DBIRTH (dispositivos[] del nacimiento). Su nombre resuelve el mapeo: si coincide con el código de un equipo del campo, sus tags nacen descubiertos; si no, pendientes. | E13: Borde (DBIRTH). | F13: GET …/tags/:tag/procedencia → lectura.reloj | G13: Si el nombre coincide con un equipo del campo, sus tags nacen descubiertos; si no, pendientes. Único: (fuente_id, nombre). Único: (id, campo_id). Único: (id, gateway_id). | H13: =COUNTIF(Columnas!$B:$B,B13) | I13: =COUNTIF(Relaciones!$A:$A,B13)
A14: Cadena de datos | B14: tag | C14: Registro de tags (descubierto del DBIRTH). Un tag es único en su campo y es del campo de su gateway (FK compuesta tag→dispositivo→fuente→gateway). La banda normal declarada aquí es la ÚNICA fuente de LimiteTag.normal; si un re-nacimiento la cambia, lo anterior queda en historial_tag. GET …/procedencia, …/inventario, …/tags/pendientes, POST …/tags/:tag/equipo. | D14: LimiteTag.texto/normal (src/entities/limites.ts); procedencia.instrumento | E14: Borde (DBIRTH); el equipo, una persona con conector:configurar cuando el borde no lo resuelve. | F14: GET …/tags/:tag/procedencia GET /api/campos/:campo/inventario GET /api/campos/:campo/tags/pendientes POST /api/campos/:campo/tags/:tag/equipo GET /api/catalogo → limites | G14: Solo el gateway que lo publica lo vuelve a declarar (409 tag-de-otro-gateway). Un nacimiento nunca deshace un mapeo manual o por regla. Si un re-nacimiento cambia banda, unidad, cadencia o calibración, lo anterior va a historial_tag. Único: (campo_id, nombre). Solo su gateway lo vuelve a declarar; un nacimiento no deshace un mapeo manual o por regla. [trigger tag_reglas: UPDATE] | H14: =COUNTIF(Columnas!$B:$B,B14) | I14: =COUNTIF(Relaciones!$A:$A,B14)
A15: Cadena de datos | B15: historial_tag | C15: Versiones anteriores de la descripción de un tag: lo que un re-nacimiento cambió (banda normal, unidad, cadencia, clase o calibración) no se pierde. La banda que regía en un instante t es la de la primera fila con reemplazado > t, o la del tag si no la hay. Solo inserción. | E15: Servidor, en el nacimiento que cambia el tag. | F15: (auditoría; la banda que regía en t) | G15: Solo inserción. Solo inserción: UPDATE, DELETE y TRUNCATE rechazados (SQLSTATE 23001). [trigger historial_tag_sin_truncate: TRUNCATE] Solo inserción: UPDATE, DELETE y TRUNCATE rechazados (SQLSTATE 23001). [trigger historial_tag_solo_insercion: UPDATE DELETE] | H15: =COUNTIF(Columnas!$B:$B,B15) | I15: =COUNTIF(Relaciones!$A:$A,B15)
A16: Cadena de datos | B16: formula | C16: Librería de fórmulas del producto, versionada e igual para todos los clientes. Una fórmula produce UNA variable (tipo_tag) de una clase de equipo. Solo aparece en un tag que ES ese cálculo (fuente calculado). Hoy la única es f1-compresor-aire (PDT-1011). | E16: Producto (librería versionada, igual para todos los clientes). | F16: GET …/tags/:tag/procedencia → calculo | G16: Una sola versión activa por (clase de equipo, variable). Índice único: CREATE UNIQUE INDEX formula_una_activa ON "trim".formula USING btree (clase_equipo, tipo_tag) WHERE activa. | H16: =COUNTIF(Columnas!$B:$B,B16) | I16: =COUNTIF(Relaciones!$A:$A,B16)
A17: Cadena de datos | B17: calculo | C17: Qué fórmula (y qué versión) produce un tag calculado. Se llena al registrar un tag de fuente calculado con la fórmula activa de (clase del equipo, tipo del tag). Es procedencia.calculo. | E17: Servidor, al registrar un tag de fuente calculado. | F17: GET …/tags/:tag/procedencia → calculo | G17: Solo en tags de fuente calculado; hoy el único es PDT-1011. | H17: =COUNTIF(Columnas!$B:$B,B17) | I17: =COUNTIF(Relaciones!$A:$A,B17)
A18: Cadena de datos | B18: calculo_entrada | C18: Tags de los que se deriva un tag calculado (PDT-1011 ← PT-1011): su reloj es «el tag del que se deriva». | E18: Servidor (librería de fórmulas). | F18: GET …/tags/:tag/procedencia | H18: =COUNTIF(Columnas!$B:$B,B18) | I18: =COUNTIF(Relaciones!$A:$A,B18)
A19: Cadena de datos | B19: calibracion | C19: Calibración vigente de un tag de medición en custodia (solo donde de verdad existe: computador de flujo, analizador de BSW, medidores de tanque). La declara el DBIRTH (metricas[].calibracion); lo anterior pasa a historial_tag. Es custodia.calibracion de la procedencia. | D19: Dispositivo.calibracion (src/entities/tipos.ts); procedencia.custodia.calibracion | E19: Borde (metricas[].calibracion del DBIRTH). | F19: GET …/tags/:tag/procedencia → custodia | G19: Solo donde de verdad hay medición en custodia. Si el borde deja de declararla, se quita (y lo anterior queda en historial_tag). | H19: =COUNTIF(Columnas!$B:$B,B19) | I19: =COUNTIF(Relaciones!$A:$A,B19)
A20: Series | B20: lectura | C20: Serie de tiempo de cada tag: lo que llega del borde en DDATA (Sparkplug B) o del historiador. Particionada por mes. De aquí sale GET /api/campos/:campo/tags/:tag/serie (SerieTag, src/entities/tipos.ts: desde, pasoH, valores con null en los huecos) y la serie de cada dispositivo y señal en las vistas. Un hueco del historiador es la AUSENCIA de filas (o una fila de calidad mala): nunca un 0. | D20: SerieTag (src/entities/tipos.ts) | E20: Borde (DDATA de Sparkplug B) o el lector del historiador. | F20: GET /api/campos/:campo/tags/:tag/serie?desde&paso serie de cada dispositivo y señal en /api/vistas/… | G20: Un hueco es ausencia de filas o calidad mala: viaja como null EN SU LUGAR, nunca como 0. Particionada por mes (hora de Colombia); sin partición por defecto. | H20: =COUNTIF(Columnas!$B:$B,B20) | I20: =COUNTIF(Relaciones!$A:$A,B20)
A21: Insumos del motor | B21: pozo | C21: Pozo de un campo (Pozo, src/entities/pozos.ts). GET /api/campos/:campo/pozos y refs.pozos["campo/pozo"]. Sin origen y sin pruebas el pozo no tiene custodia: no se le asigna caudal. | D21: Pozo (src/entities/pozos.ts) | E21: Registro de ingeniería / maestro de pozos del cliente. | F21: GET /api/campos/:campo/pozos refs.pozos["campo/pozo"] GET /api/catalogo → campos[c].pozos | G21: Sin origen y sin pruebas no tiene custodia: no se le asigna caudal. | H21: =COUNTIF(Columnas!$B:$B,B21) | I21: =COUNTIF(Relaciones!$A:$A,B21)
A22: Insumos del motor | B22: prueba_pozo | C22: Prueba de pozo (Prueba, src/entities/pozos.ts; Pozo.pruebas). Rige desde su fecha hasta la siguiente; antes de la primera rige la primera (pruebaEn). Con el factor de asignación del mes da el crudo del pozo. | D22: Prueba (src/entities/pozos.ts) | E22: Borde (separador de prueba automatizado) o estimación de la propia electrosumergible. | F22: GET /api/campos/:campo/pozos → pruebas[] | G22: Rige desde su fecha hasta la siguiente; antes de la primera rige la primera (pruebaEn). | H22: =COUNTIF(Columnas!$B:$B,B22) | I22: =COUNTIF(Relaciones!$A:$A,B22)
A23: Insumos del motor | B23: evento | C23: Supertipo de los eventos del borde: un id único para todo el sistema (refs.eventos["id"] del contrato). clase pozo → evento_pozo, bomba → parada_bomba, servicio → evento_servicio. | D23: refs.eventos (clave común de EventoPozo y EventoBomba) | E23: Servidor, al registrar cualquier evento del borde. | F23: (interna: destino de las FK a «un evento») | G23: Un id es único en todo el sistema. Solo inserción. Único: (id, clase, campo_id, activo). Solo inserción: UPDATE, DELETE y TRUNCATE rechazados (SQLSTATE 23001). [trigger evento_sin_truncate: TRUNCATE] Solo inserción: UPDATE, DELETE y TRUNCATE rechazados (SQLSTATE 23001). [trigger evento_solo_insercion: UPDATE DELETE] | H23: =COUNTIF(Columnas!$B:$B,B23) | I23: =COUNTIF(Relaciones!$A:$A,B23)
A24: Insumos del motor | B24: evento_pozo | C24: Evento del controlador de un pozo (EventoPozo, src/entities/pozos.ts): variador, controlador de bombeo o válvula de cabeza. GET /api/campos/:campo/pozos/eventos y refs.eventos. Es la unidad de cobro del libro. Eventos que se pisan en el mismo pozo: se guardan como llegan y el motor los normaliza (intervalosEfectivos, libro.ts) — capítulo 4. | D24: EventoPozo (src/entities/pozos.ts) | E24: Borde (controlador del pozo: variador, controlador de bombeo, válvula de cabeza). | F24: GET /api/campos/:campo/pozos/eventos?desde&hasta refs.eventos | G24: La hora la pone el PLC y no se corrige: solo se cierra (fin) una vez. Eventos que se pisan: se guardan como llegan y el motor los normaliza (un paro manda sobre un HZ; entre iguales, el primero). Solo inserción: UPDATE, DELETE y TRUNCATE rechazados (SQLSTATE 23001). [trigger evento_pozo_sin_truncate: TRUNCATE] La hora del PLC no se corrige: solo se pone fin a un evento abierto (una vez) y, en una parada, la firma (una vez); no se borra. [trigger evento_pozo_solo_cierre: UPDATE DELETE] | H24: =COUNTIF(Columnas!$B:$B,B24) | I24: =COUNTIF(Relaciones!$A:$A,B24)
A25: Insumos del motor | B25: evento_servicio | C25: Caída de un servicio o equipo de proceso que apaga o frena pozos (EventoServicio, src/entities/pozos.ts). GET /api/campos/:campo/servicios/eventos. OJO: el tipo TS exige fin; la base admite NULL (servicio caído ahora) y el endpoint de insumo decide cómo entregarlo (capítulo 4, Huecos). | D25: EventoServicio (src/entities/pozos.ts) | E25: Borde (PLC o IED del servicio). | F25: GET /api/campos/:campo/servicios/eventos?desde&hasta | G25: fin NULL = sigue caído (el tipo TS todavía exige fin: ver Huecos). Solo inserción: UPDATE, DELETE y TRUNCATE rechazados (SQLSTATE 23001). [trigger evento_servicio_sin_truncate: TRUNCATE] La hora del PLC no se corrige: solo se pone fin a un evento abierto (una vez) y, en una parada, la firma (una vez); no se borra. [trigger evento_servicio_solo_cierre: UPDATE DELETE] | H25: =COUNTIF(Columnas!$B:$B,B25) | I25: =COUNTIF(Relaciones!$A:$A,B25)
A26: Insumos del motor | B26: parada_bomba | C26: Parada (o pérdida de caudal) de una bomba de la línea según su PLC (EventoBomba, src/entities/bombas.ts). GET /api/campos/:campo/bombas/:equipo/paradas. La parte NO viene escrita a mano: sale de la primera alarma o de la firma de las señales al parar. | D26: EventoBomba (src/entities/bombas.ts) | E26: Borde (PLC de la bomba); la firma, el servidor con las lecturas del instante de parar. | F26: GET /api/campos/:campo/bombas/:equipo/paradas?desde&hasta | G26: La parte nunca se escribe a mano: sale de la primera alarma o de la firma. La firma se pone una vez y no cambia al cerrarse la parada. Solo inserción: UPDATE, DELETE y TRUNCATE rechazados (SQLSTATE 23001). [trigger parada_bomba_sin_truncate: TRUNCATE] La hora del PLC no se corrige: solo se pone fin a un evento abierto (una vez) y, en una parada, la firma (una vez); no se borra. [trigger parada_bomba_solo_cierre: UPDATE DELETE] | H26: =COUNTIF(Columnas!$B:$B,B26) | I26: =COUNTIF(Relaciones!$A:$A,B26)
A27: Insumos del motor | B27: punto_medicion | C27: Punto de medición oficial de un campo (OrigenPmo de src/entities/insumos.ts, y Equipo.fiscal). GET /api/catalogo → medicion.origen y produccion-diaria.origen. Uno por campo: el motor lleva un fiscal por campo. | D27: OrigenPmo (src/entities/insumos.ts) y Equipo.fiscal | E27: Implementación (registro del punto de medición oficial). | F27: GET /api/campos/:campo/produccion-diaria → origen GET /api/catalogo → medicion.origen | G27: Uno por campo. | H27: =COUNTIF(Columnas!$B:$B,B27) | I27: =COUNTIF(Relaciones!$A:$A,B27)
A28: Insumos del motor | B28: mes_fiscal | C28: Estado fiscal de un mes de un campo (la parte publicado de ProduccionMes, src/entities/pozos.ts). Cada campo publica su mes por su cuenta. El calendario de GET /api/catalogo sale de aquí (publicado = todos los campos con fiscal lo publicaron). | D28: ProduccionMes.publicado (src/entities/pozos.ts); Mes (libro.ts) | E28: Servidor, cuando el campo publica su mes fiscal (contabilidad de hidrocarburos). | F28: GET /api/campos/:campo/produccion-diaria → meses[].publicado GET /api/catalogo → calendario | G28: Cada campo publica su mes por su cuenta. | H28: =COUNTIF(Columnas!$B:$B,B28) | I28: =COUNTIF(Relaciones!$A:$A,B28)
A29: Insumos del motor | B29: produccion_fiscal_diaria | C29: Barriles netos de cada día en el punto de medición oficial (ProduccionMes.dias). GET /api/campos/:campo/produccion-diaria arma por mes el arreglo dias[] con null donde no hay fila o bbl es NULL. Un día sin dato del computador de flujo NO es cero: no entra ni en lo real ni en el potencial y el libro no se publica. | D29: ProduccionMes.dias (src/entities/pozos.ts) | E29: Borde (computador de flujo del punto de medición oficial, ticket diario). | F29: GET /api/campos/:campo/produccion-diaria?desde&hasta | G29: NULL o día ausente = sin dato, nunca 0. El día de hoy es parcial (cerrado = false). | H29: =COUNTIF(Columnas!$B:$B,B29) | I29: =COUNTIF(Relaciones!$A:$A,B29)
A30: Insumos del motor | B30: metrologia_campo | C30: Registro de metrología de un campo, versionado (MetrologiaCampo, src/entities/metrologia.ts). GET /api/campos/:campo/metrologia y catalogo.medicion.metrologia toman la fila vigente. Con °API y la producción fiscal publicada se escoge la fila de la Fig. 10.2 (banda_regulatoria); un presupuesto demostrado (API MPMS 13.3 / ISO 5168) la reemplaza. | D30: MetrologiaCampo (src/entities/metrologia.ts) | E30: Laboratorio / metrología del cliente. | F30: GET /api/campos/:campo/metrologia GET /api/catalogo → medicion.metrologia | G30: °API NULL = banda no verificable: el libro no se publica (nunca 0 °API). | H30: =COUNTIF(Columnas!$B:$B,B30) | I30: =COUNTIF(Relaciones!$A:$A,B30)
... A35: Insumos del motor | B35: alarma_tag | C35: Base maestra de alarmas (ISA-18.2): el punto de alarma de cada tag con su norma u hoja de datos (Alarma de src/entities/bombas.ts, LimiteTag.alarma de limites.ts). Versionada y de solo inserción: rige la fila más nueva con vigente_desde ≤ t. Sin fila, el vigía responde «sin límite». | D35: Alarma (bombas.ts); LimiteTag.alarma (limites.ts) | E35: Ingeniería de confiabilidad del cliente (base maestra de alarmas, ISA-18.2). | F35: GET /api/catalogo → limites[tag].alarma | G35: Sin alarma, el vigía responde «sin límite». Solo inserción: un cambio es una fila nueva con su fecha. Solo inserción: UPDATE, DELETE y TRUNCATE rechazados (SQLSTATE 23001). [trigger alarma_tag_sin_truncate: TRUNCATE] Solo inserción: UPDATE, DELETE y TRUNCATE rechazados (SQLSTATE 23001). [trigger alarma_tag_solo_insercion: UPDATE DELETE] | H35: =COUNTIF(Columnas!$B:$B,B35) | I35: =COUNTIF(Relaciones!$A:$A,B35)
A36: Insumos del motor | B36: ajuste_variador | C36: Ajustes de protección del variador de cada electrosumergible (configuración del pozo): banda normal y alarma de sus cinco señales. Hoy NO tienen endpoint en el contrato: referencia/insumos/<campo>/electrosumergibles.json los trae con "endpoint": null (Pendiente del lado del servidor). | D36: Senal.normal y Senal.alarma de la electrosumergible (src/entities/esp.ts) | E36: Borde (lectura de los ajustes de protección del variador). | F36: (sin endpoint: referencia/insumos/<campo>/electrosumergibles.json, endpoint null) | H36: =COUNTIF(Columnas!$B:$B,B36) | I36: =COUNTIF(Relaciones!$A:$A,B36)
A37: Insumos del motor | B37: modo_falla | C37: Modos de falla de ISO 14224:2016, Anexo B (tablas B.6–B.15): MODOS de src/entities/iso14224.ts, con el nombre en palabras de campo (MODO_EN_CAMPO de catalogo.ts). Es «lo que se vio». | D37: Modo (src/entities/iso14224.ts) | E37: Producto (ISO 14224). | F37: GET /api/catalogo → catalogosDanos GET /api/vistas/paradas/:evento/opciones | H37: =COUNTIF(Columnas!$B:$B,B37) | I37: =COUNTIF(Relaciones!$A:$A,B37)
A38: Insumos del motor | B38: mecanismo_falla | C38: Mecanismos de falla de ISO 14224:2016 Table B.2 (MECANISMOS de src/entities/iso14224.ts). Transcrita, pendiente de cotejo con la norma comprada. Solo lo de degradación se proyecta con una tendencia. | D38: Mecanismo (src/entities/iso14224.ts) | E38: Producto (ISO 14224 Table B.2, pendiente de cotejo). | F38: POST /api/analisis/:evento (valida) | G38: Solo lo de degradación se proyecta con una tendencia. | H38: =COUNTIF(Columnas!$B:$B,B38) | I38: =COUNTIF(Relaciones!$A:$A,B38)
A39: Insumos del motor | B39: causa_raiz | C39: Las cinco categorías de causa raíz de primer nivel de ISO 14224 Table B.3 (CAUSAS_RAIZ de src/entities/iso14224.ts). | D39: CAUSAS_RAIZ (src/entities/iso14224.ts) | E39: Producto (ISO 14224 Table B.3). | F39: POST /api/analisis/:evento (valida) | H39: =COUNTIF(Columnas!$B:$B,B39) | I39: =COUNTIF(Relaciones!$A:$A,B39)
A40: Insumos del motor | B40: modo_por_clase | C40: Qué modos aplican a cada clase de equipo (ISO 14224 B.2.6; MODOS_POR_CLASE de src/entities/iso14224.ts). | D40: MODOS_POR_CLASE (src/entities/iso14224.ts) | E40: Producto. | F40: GET /api/catalogo → catalogosDanos | G40: Único: (clase_iso, orden). | H40: =COUNTIF(Columnas!$B:$B,B40) | I40: =COUNTIF(Relaciones!$A:$A,B40)
A41: Insumos del motor | B41: clase_catalogo | C41: Clases del catálogo de daños (ClaseCatalogo y NOMBRE_CLASE_EQUIPO de src/entities/catalogo.ts) y la familia de partes de cada una. | D41: ClaseCatalogo, Catalogo.clase (src/entities/catalogo.ts) | E41: Producto. | F41: GET /api/catalogo → catalogosDanos[equipo].clase | G41: Único: (familia). | H41: =COUNTIF(Columnas!$B:$B,B41) | I41: =COUNTIF(Relaciones!$A:$A,B41)
A42: Insumos del motor | B42: clase_iso_catalogo | C42: De la clase ISO del registro y el papel de la bomba al catálogo de daños (claseDeCatalogo de src/entities/catalogo.ts). Se busca primero el papel exacto y si no, *. Una clase sin fila no tiene catálogo de partes. | D42: claseDeCatalogo (src/entities/catalogo.ts) | E42: Producto. | F42: GET /api/catalogo → catalogosDanos | G42: Se busca el papel exacto y si no, *. | H42: =COUNTIF(Columnas!$B:$B,B42) | I42: =COUNTIF(Relaciones!$A:$A,B42)
A43: Insumos del motor | B43: parte | C43: Partes (ítem mantenible, nivel 8 de ISO 14224) de cada familia (Parte de src/entities/partes.ts; PARTES_INYECCION, PARTES_MULTIFASICA, PARTES_ESP). Librería del producto, versionada con el código. | D43: Parte (src/entities/partes.ts) | E43: Producto. | F43: GET /api/catalogo → catalogosDanos[equipo].partes | G43: Único: (familia, orden). | H43: =COUNTIF(Columnas!$B:$B,B43) | I43: =COUNTIF(Relaciones!$A:$A,B43)
A44: Insumos del motor | B44: parte_variable | C44: Variables de la familia que dicen algo de la parte, con su papel: avisa (anticipa), causa (la daña) o confirma (cambia cuando ya empezó). Parte.variables de partes.ts. | D44: Parte.variables (src/entities/partes.ts) | E44: Producto. | F44: GET /api/catalogo → catalogosDanos | H44: =COUNTIF(Columnas!$B:$B,B44) | I44: =COUNTIF(Relaciones!$A:$A,B44)
A45: Insumos del motor | B45: parte_modo | C45: Modos de falla que produce la parte (Parte.modos). Además de estos, toda parte admite OTH («otro»: modosDeParte). | D45: Parte.modos (src/entities/partes.ts) | E45: Producto. | F45: GET /api/catalogo → catalogosDanos | G45: Toda parte admite además OTH (modosDeParte). | H45: =COUNTIF(Columnas!$B:$B,B45) | I45: =COUNTIF(Relaciones!$A:$A,B45)
A46: Insumos del motor | B46: mapeo_catalogo_sap | C46: Cómo se dice cada código de TRIM en el perfil de catálogo de SAP PM del cliente: parte → catálogo B (parte del objeto), modo → C (daño), mecanismo → daño o causa según el perfil, causa raíz → 5 (causa). Se llena en la implementación; el demo no trae filas. | E46: Implementación, con el perfil de catálogo de SAP del cliente. | F46: POST /api/sap/avisos (traduce parte y modo al catálogo del cliente) | H46: =COUNTIF(Columnas!$B:$B,B46) | I46: =COUNTIF(Relaciones!$A:$A,B46)
A47: Insumos del motor | B47: perfil_bomba_primera_alarma | C47: Interruptores de disparo que el PLC de ESTA máquina congela como primera alarma, y la parte que cada uno protege (Maquina.primerasAlarmas). Un tag que no está aquí no identifica la parte: queda en la evidencia. | D47: Maquina.primerasAlarmas (src/entities/bombas.ts) | E47: Ingeniería del cliente. | F47: GET /api/catalogo → perfilesBomba[].primerasAlarmas | G47: Un tag que la máquina no declara no identifica la parte: queda en la evidencia. | H47: =COUNTIF(Columnas!$B:$B,B47) | I47: =COUNTIF(Relaciones!$A:$A,B47)
A48: Configuración firmada | B48: version_config | C48: Una versión firmada de la configuración (Version, src/entities/configuracion.ts). GET /api/configuracion/historial (de la más vieja a la vigente) y POST /api/configuracion. Solo inserción. version = base + 1 con la clave primaria hace de candado optimista: si otro firmó en el medio, el INSERT choca y el servidor responde 409 version-cambio. | D48: Version (src/entities/configuracion.ts) | E48: Servidor al firmar: metas:firmar (metas, precio, regla de cierre) y/o config:firmar (lo técnico), sobre los campos de la persona (camposTocados). | F48: GET /api/configuracion/historial POST /api/configuracion GET /api/configuracion (opcional) | G48: Solo inserción. version = base + 1: si otro firmó en el medio, 409 version-cambio. validarConfig (422) con la hora del servidor: nada de un mes cerrado cambia; el programa es inmutable hacia atrás. Al confirmar, el JSON y lo normalizado dicen lo mismo y todo campo trae un tramo. Al confirmar: todo campo trae un tramo y el JSON firmado = la forma normalizada. [trigger version_config_coherente: INSERT, diferido] Solo inserción: UPDATE, DELETE y TRUNCATE rechazados (SQLSTATE 23001). [trigger version_config_sin_truncate: TRUNCATE] Solo inserción: UPDATE, DELETE y TRUNCATE rechazados (SQLSTATE 23001). [trigger version_config_solo_insercion: UPDATE DELETE] | H48: =COUNTIF(Columnas!$B:$B,B48) | I48: =COUNTIF(Relaciones!$A:$A,B48)
A49: Configuración firmada | B49: membrete | C49: Config.empresa de cada versión: el nombre de la empresa en el membrete de los informes. Es de la empresa, no de un campo (firma config:firmar). | D49: Config.empresa | E49: Servidor al firmar (config:firmar). | F49: GET /api/configuracion/historial | G49: Solo inserción. Solo inserción: UPDATE, DELETE y TRUNCATE rechazados (SQLSTATE 23001). [trigger membrete_sin_truncate: TRUNCATE] Solo inserción: UPDATE, DELETE y TRUNCATE rechazados (SQLSTATE 23001). [trigger membrete_solo_insercion: UPDATE DELETE] | H49: =COUNTIF(Columnas!$B:$B,B49) | I49: =COUNTIF(Relaciones!$A:$A,B49)
A50: Configuración firmada | B50: perfil_campo | C50: Perfil firmado de cada campo en cada versión (PerfilCampo de configuracion.ts): qué familias de equipo tiene y qué hace con el gas. Una familia apagada sale de la vigilancia (riesgo, predicciones, bombas) pero lo que pierde se sigue contando en el libro. Un campo de Config.campos es una fila aquí. | D50: PerfilCampo (src/entities/configuracion.ts) | E50: Servidor al firmar (config:firmar). | F50: GET /api/configuracion/historial | G50: Solo inserción. Sin perfil firmado el campo no tiene ninguna familia (perfilDe). Solo inserción: UPDATE, DELETE y TRUNCATE rechazados (SQLSTATE 23001). [trigger perfil_campo_sin_truncate: TRUNCATE] Solo inserción: UPDATE, DELETE y TRUNCATE rechazados (SQLSTATE 23001). [trigger perfil_campo_solo_insercion: UPDATE DELETE] | H50: =COUNTIF(Columnas!$B:$B,B50) | I50: =COUNTIF(Relaciones!$A:$A,B50)
A51: Configuración firmada | B51: tramo_meta | C51: Tramo de meta de un campo (TramoMeta de configuracion.ts): rige desde su día (hora de Colombia) hasta que empiece el siguiente, con el precio neto y el máximo sin causa de la misma fecha. La meta global es la suma de los campos y nunca se guarda. Firma metas:firmar. | D51: TramoMeta (src/entities/configuracion.ts) | E51: Servidor al firmar (metas:firmar). | F51: GET /api/configuracion/historial POST /api/configuracion | G51: Solo inserción. Un tramo nuevo o cambiado no empieza antes del primer día del mes en curso (422). Sin tramo vigente: «sin meta firmada» (nunca 0). Solo inserción: UPDATE, DELETE y TRUNCATE rechazados (SQLSTATE 23001). [trigger tramo_meta_sin_truncate: TRUNCATE] Solo inserción: UPDATE, DELETE y TRUNCATE rechazados (SQLSTATE 23001). [trigger tramo_meta_solo_insercion: UPDATE DELETE] | H51: =COUNTIF(Columnas!$B:$B,B51) | I51: =COUNTIF(Relaciones!$A:$A,B51)
A52: Configuración firmada | B52: tanque | C52: Tanque de agua de una bomba de reinyección (TanqueAgua de configuracion.ts), firmado. Se busca por (campo, bomba): como máximo uno por bomba. Con el nivel y el aforo da el colchón de horas. Firma config:firmar. | D52: TanqueAgua (src/entities/configuracion.ts) | E52: Servidor al firmar (config:firmar). | F52: GET /api/configuracion/historial | G52: Solo inserción. Uno por (campo, bomba); alto-alto 50–98 %. Único: (version, campo_id, bomba). Único: (version, orden). Solo inserción: UPDATE, DELETE y TRUNCATE rechazados (SQLSTATE 23001). [trigger tanque_sin_truncate: TRUNCATE] Solo inserción: UPDATE, DELETE y TRUNCATE rechazados (SQLSTATE 23001). [trigger tanque_solo_insercion: UPDATE DELETE] | H52: =COUNTIF(Columnas!$B:$B,B52) | I52: =COUNTIF(Relaciones!$A:$A,B52)
A53: Configuración firmada | B53: respaldo | C53: Respaldo de una bomba de la línea (RespaldoBomba de configuracion.ts): cuánto fluido libre toma el equipo en paralelo cuando ella para. Uno por (campo, equipo). Cambia el colchón, el orden de cierre y el texto del WhatsApp de la parada. Firma config:firmar. | D53: RespaldoBomba (src/entities/configuracion.ts) | E53: Servidor al firmar (config:firmar). | F53: GET /api/configuracion/historial | G53: Solo inserción. Uno por (campo, equipo). Único: (version, orden). Solo inserción: UPDATE, DELETE y TRUNCATE rechazados (SQLSTATE 23001). [trigger respaldo_sin_truncate: TRUNCATE] Solo inserción: UPDATE, DELETE y TRUNCATE rechazados (SQLSTATE 23001). [trigger respaldo_solo_insercion: UPDATE DELETE] | H53: =COUNTIF(Columnas!$B:$B,B53) | I53: =COUNTIF(Relaciones!$A:$A,B53)
A54: Configuración firmada | B54: parada_programada | C54: Programa de paradas aprobado (ParadaProgramada de configuracion.ts). Un evento del equipo que empieza dentro de [desde, hasta] es programado. Inmutable hacia atrás: una parada solo entra, sale o se mueve antes de empezar (lo revisa validarConfig contra la versión anterior). Firma config:firmar. Ids recomendados PR-{campo}-{equipo}-{fecha} (o los asigna el servidor). | D54: ParadaProgramada (src/entities/configuracion.ts) | E54: Servidor al firmar (config:firmar). | F54: GET /api/configuracion/historial insumo del motor: Insumos.programa | G54: Solo inserción. Una parada nueva o movida empieza después de ahora; la que ya empezó no cambia ni se quita (422). Único: (version, orden). Solo inserción: UPDATE, DELETE y TRUNCATE rechazados (SQLSTATE 23001). [trigger parada_programada_sin_truncate: TRUNCATE] Solo inserción: UPDATE, DELETE y TRUNCATE rechazados (SQLSTATE 23001). [trigger parada_programada_solo_insercion: UPDATE DELETE] | H54: =COUNTIF(Columnas!$B:$B,B54) | I54: =COUNTIF(Relaciones!$A:$A,B54)
A55: Personas | B55: rol | C55: Roles del producto (Rol de src/entities/tipos.ts; ROLES de roles.ts). Los fija el producto: el gerente decide quién tiene cada rol, no qué hace el rol. visible=false son los de la versión 2 (plan, cont, reg), que no se ofrecen. | D55: Rol (src/entities/tipos.ts; ROLES en roles.ts) | E55: Producto. | F55: GET /api/sesion → rolId, nivel | H55: =COUNTIF(Columnas!$B:$B,B55) | I55: =COUNTIF(Relaciones!$A:$A,B55)
A56: Personas | B56: capacidad | C56: Las nueve capacidades (Capacidad y CAPACIDAD_NOMBRE de src/entities/tipos.ts): cada una es un permiso que el servidor revisa en un endpoint (403 sin ella). | D56: Capacidad (src/entities/tipos.ts) | E56: Producto. | F56: GET /api/sesion → capacidades | H56: =COUNTIF(Columnas!$B:$B,B56) | I56: =COUNTIF(Relaciones!$A:$A,B56)
A57: Personas | B57: rol_capacidad | C57: Reparto de capacidades por rol (Rol.puede de roles.ts). Las capacidades de la sesión salen de aquí (más lo que cada una incluye). | D57: Rol.puede (src/entities/roles.ts) | E57: Producto. | F57: GET /api/sesion → capacidades | H57: =COUNTIF(Columnas!$B:$B,B57) | I57: =COUNTIF(Relaciones!$A:$A,B57)
A58: Personas | B58: usuario | C58: Registro de personas (Usuario de src/entities/usuarios.ts). GET/POST /api/usuarios, PATCH /api/usuarios/:id. Nadie se borra: quien ya no debe entrar queda suspendido y su nombre sigue en lo que firmó. Correo único en minúsculas; WhatsApp en E.164 único entre los no suspendidos (es la identidad del webhook). | D58: Usuario / PersonaVisible (src/entities/usuarios.ts) | E58: Servidor, por quien tiene usuarios:administrar (gerente de activo). | F58: GET /api/usuarios POST /api/usuarios PATCH /api/usuarios/:id GET /api/sesion | G58: Nadie se borra: se suspende. Nadie cambia sus propios campos, ni se suspende ni se quita el rol (403). Nadie otorga campos que no tiene (403). Tiene que quedar un gerente activo (409). Sin usuarios:administrar, GET devuelve la forma mínima (registroVisible). Índice único: CREATE UNIQUE INDEX usuario_correo_unico ON "trim".usuario USING btree (lower(btrim(correo))). Índice único: CREATE UNIQUE INDEX usuario_telefono_unico ON "trim".usuario USING btree (telefono) WHERE (estado <> 'suspendido'::text). Al confirmar: queda un gerente activo y cada persona tiene «todos» o al menos un campo. [trigger usuario_coherente: INSERT UPDATE, diferido] Nadie se borra; alertas solo en roles con alertas. [trigger usuario_reglas: INSERT UPDATE DELETE] Nadie se borra; alertas solo en roles con alertas. [trigger usuario_sin_truncate: TRUNCATE] | H58: =COUNTIF(Columnas!$B:$B,B58) | I58: =COUNTIF(Relaciones!$A:$A,B58)
A59: Personas | B59: usuario_campo | C59: Campos asignados a una persona cuando no tiene «todos» (camposAsignados de usuarios.ts). La capacidad dice QUÉ puede hacer; los campos, DÓNDE: toda lectura y escritura se limita a ellos. | D59: Usuario.campos (src/entities/usuarios.ts) | E59: Servidor (usuarios:administrar). | F59: GET /api/usuarios GET /api/sesion → campos | G59: «todos» o al menos un campo. Al confirmar: queda un gerente activo y cada persona tiene «todos» o al menos un campo. [trigger usuario_campo_coherente: INSERT DELETE, diferido] | H59: =COUNTIF(Columnas!$B:$B,B59) | I59: =COUNTIF(Relaciones!$A:$A,B59)
A60: Personas | B60: identidad_oidc | C60: De la identidad del servicio de SSO del cliente (OIDC: iss + sub del token) a la persona de TRIM. TRIM no guarda contraseñas. | E60: Servidor, en el primer inicio de sesión de una persona invitada. | F60: (todas: resuelve la persona del token) | H60: =COUNTIF(Columnas!$B:$B,B60) | I60: =COUNTIF(Relaciones!$A:$A,B60)
A61: Personas | B61: cambio_acceso | C61: Rastro de cada cambio de acceso (CambioAcceso de usuarios.ts): quién, cuándo, a quién, qué y por qué. GET /api/usuarios/historial (solo con usuarios:administrar). Solo inserción. | D61: CambioAcceso (src/entities/usuarios.ts) | E61: Servidor, en la misma transacción del cambio de acceso. | F61: GET /api/usuarios/historial POST /api/usuarios PATCH /api/usuarios/:id | G61: Solo inserción. Solo inserción: UPDATE, DELETE y TRUNCATE rechazados (SQLSTATE 23001). [trigger cambio_acceso_sin_truncate: TRUNCATE] Solo inserción: UPDATE, DELETE y TRUNCATE rechazados (SQLSTATE 23001). [trigger cambio_acceso_solo_insercion: UPDATE DELETE] | H61: =COUNTIF(Columnas!$B:$B,B61) | I61: =COUNTIF(Relaciones!$A:$A,B61)
A62: Lo que se lee de SAP PM | B62: equipo_sap | C62: Identidad del activo en el maestro de SAP PM (identidadSap de src/entities/sap.ts): número de equipo y ubicación técnica. Se asocia en Conectores. GET /api/sap/equipos?campo y GET /api/sap/equipos/:equipo → identidad. En el demo sale de una regla fija. | D62: identidadSap (src/entities/sap.ts) | E62: Sincronización con el maestro de SAP; la asociación, en Conectores. | F62: GET /api/sap/equipos?campo GET /api/sap/equipos/:equipo → identidad | G62: Único: (equipo_sap). | H62: =COUNTIF(Columnas!$B:$B,B62) | I62: =COUNTIF(Relaciones!$A:$A,B62)
A63: Lo que se lee de SAP PM | B63: clase_orden_sap | C63: Mapeo de las clases de orden de la operadora a las tres de TRIM (ClaseOrden: PM01 correctivo, PM02 preventivo, PM03 predictivo). Se configura en la implementación. | D63: ClaseOrden (src/entities/sap.ts) | E63: Implementación. | F63: GET /api/sap/ordenes → clase | H63: =COUNTIF(Columnas!$B:$B,B63) | I63: =COUNTIF(Relaciones!$A:$A,B63)
A64: Lo que se lee de SAP PM | B64: aviso_sap | C64: Avisos de mantenimiento de SAP PM (AvisoSap de src/entities/sap.ts): los que TRIM envía (POST /api/sap/avisos, origen trim) y los creados directo en SAP (origen sap), sincronizados. GET /api/sap/avisos. Uno abierto por (campo, equipo): índice único parcial; el POST responde 409 con el número del abierto. | D64: AvisoSap (src/entities/sap.ts) | E64: Servidor (POST con sap:aviso, origen trim) y la sincronización con SAP (origen sap, cerrado, orden). | F64: GET /api/sap/avisos?campos POST /api/sap/avisos | G64: Uno abierto por (campo, equipo): 409 con el número del abierto. Descripción de 8 caracteres o más (422 campo descripcion). número, creado, creadoPor, origen y cerrado los pone el servidor. Índice único: CREATE UNIQUE INDEX aviso_sap_uno_abierto ON "trim".aviso_sap USING btree (campo_id, equipo) WHERE (NOT cerrado). | H64: =COUNTIF(Columnas!$B:$B,B64) | I64: =COUNTIF(Relaciones!$A:$A,B64)
A65: Lo que se lee de SAP PM | B65: orden_sap | C65: Órdenes de trabajo de SAP PM (OrdenSap de src/entities/sap.ts), leídas de SAP: las crea, libera y cierra el planeador allá. GET /api/sap/ordenes (el front suma las horas por clase). Con la parada del PLC (evento_id) dan los tres relojes de ISO 14224. En el demo se derivan del PLC con una regla fija. | D65: OrdenSap (src/entities/sap.ts) | E65: Sincronización con SAP (solo lectura para TRIM). | F65: GET /api/sap/ordenes?campos GET /api/vistas/relojes | G65: TRIM no crea órdenes. Al pasar a REL con técnico asignado sale el WhatsApp trim_orden_liberada. Índice único: CREATE UNIQUE INDEX orden_sap_un_aviso ON "trim".orden_sap USING btree (aviso) WHERE (aviso IS NOT NULL). | H65: =COUNTIF(Columnas!$B:$B,B65) | I65: =COUNTIF(Relaciones!$A:$A,B65)
A66: Lo que se lee de SAP PM | B66: confirmacion_sap | C66: Confirmaciones de horas de una orden en SAP (AFRU), para auditar orden_sap.horas_reales. Opcional: el demo no trae detalle. | E66: Sincronización con SAP. | F66: (auditoría de horasReales) | H66: =COUNTIF(Columnas!$B:$B,B66) | I66: =COUNTIF(Relaciones!$A:$A,B66)
A67: Lo que se lee de SAP PM | B67: material_sap | C67: Maestro de materiales de los repuestos críticos (SAP MM). | D67: RepuestoOrden.material / Repuesto.material (src/entities/sap.ts) | E67: Sincronización con SAP MM. | F67: GET /api/sap/equipos/:equipo → repuestos | H67: =COUNTIF(Columnas!$B:$B,B67) | I67: =COUNTIF(Relaciones!$A:$A,B67)
A68: Lo que se lee de SAP PM | B68: repuesto_orden | C68: Repuestos reservados en una orden (RepuestoOrden de src/entities/sap.ts). | D68: RepuestoOrden (src/entities/sap.ts) | E68: Sincronización con SAP. | F68: GET /api/sap/ordenes → repuestos | H68: =COUNTIF(Columnas!$B:$B,B68) | I68: =COUNTIF(Relaciones!$A:$A,B68)
A69: Lo que se lee de SAP PM | B69: stock_sap | C69: Stock de libre utilización de un repuesto crítico en la bodega del campo (Repuesto de src/entities/sap.ts). GET /api/sap/equipos/:equipo → repuestos. | D69: Repuesto (src/entities/sap.ts) | E69: Sincronización con SAP MM. | F69: GET /api/sap/equipos/:equipo → repuestos | H69: =COUNTIF(Columnas!$B:$B,B69) | I69: =COUNTIF(Relaciones!$A:$A,B69)
A70: Lo que se lee de SAP PM | B70: repuesto_equipo | C70: Qué equipos usan un repuesto (Repuesto.equipos). Un material del campo sin filas aquí es de la flota de electrosumergibles del campo (repuestosDe de sap.ts). | D70: Repuesto.equipos (src/entities/sap.ts) | E70: Implementación / SAP (lista de materiales del equipo). | F70: GET /api/sap/equipos/:equipo → repuestos | G70: Un material sin filas aquí es de la flota de electrosumergibles del campo. | H70: =COUNTIF(Columnas!$B:$B,B70) | I70: =COUNTIF(Relaciones!$A:$A,B70)
A71: Lo que entra a mano y WhatsApp | B71: plantilla_whatsapp | C71: Las diez plantillas aprobadas por Meta (PLANTILLAS de src/entities/mensajes.ts). El mensaje que inicia la empresa tiene que ser una de ellas; el texto de cada mensaje es exactamente su cuerpo con los parámetros. | D71: PLANTILLAS (src/entities/mensajes.ts) | E71: Producto (aprobadas por Meta). | F71: GET /api/mensajes → plantilla | G71: Único: (nombre). | H71: =COUNTIF(Columnas!$B:$B,B71) | I71: =COUNTIF(Relaciones!$A:$A,B71)
A72: Lo que entra a mano y WhatsApp | B72: prediccion | C72: Registro de predicciones del vigía (PrediccionVigia de src/entities/aciertos.ts). Se guarda cuando sale, con su ventana; la calificación (acierto, intervenida, falsa alarma) se agrega una sola vez al vencer (calificar). GET /api/vistas/predicciones. Nada se califica hacia atrás: el registro empieza con la puesta en marcha. | D72: PrediccionVigia (src/entities/aciertos.ts) | E72: Servidor (el vigía al emitir; la calificación al vencer). | F72: GET /api/vistas/predicciones?campos | G72: Se guarda al emitirse y solo se le agrega la calificación, una vez. Nada se califica hacia atrás. Lo emitido no cambia; la calificación se agrega una vez; no se borra. [trigger prediccion_califica: UPDATE DELETE] Solo inserción: UPDATE, DELETE y TRUNCATE rechazados (SQLSTATE 23001). [trigger prediccion_sin_truncate: TRUNCATE] | H72: =COUNTIF(Columnas!$B:$B,B72) | I72: =COUNTIF(Relaciones!$A:$A,B72)
A73: Lo que entra a mano y WhatsApp | B73: respuesta_entrante | C73: Mensajes entrantes del webhook de WhatsApp (POST /api/webhooks/whatsapp), ya con la firma X-Hub-Signature-256 válida. La clave primaria es el id de Meta (messages[].id): Meta reintenta y el segundo intento choca (deduplicación). Se guarda aceptado, en curso (un paso del diálogo que pide el siguiente: la parte o lo que vio) o descartado, con el motivo. Solo inserción. | E73: Servidor, al recibir el webhook firmado de Meta. | F73: POST /api/webhooks/whatsapp | G73: Firma X-Hub-Signature-256 válida o 401 (no se guarda). Dedupe por id de Meta; siempre 200 a Meta. El evento sale solo del context.id (de mensaje o de mensaje_libre). Un paso del diálogo que pide lo que falta queda en-curso; la respuesta_parada entra con el último. Solo inserción. Solo inserción: UPDATE, DELETE y TRUNCATE rechazados (SQLSTATE 23001). [trigger respuesta_entrante_sin_truncate: TRUNCATE] Solo inserción: UPDATE, DELETE y TRUNCATE rechazados (SQLSTATE 23001). [trigger respuesta_entrante_solo_insercion: UPDATE DELETE] | H73: =COUNTIF(Columnas!$B:$B,B73) | I73: =COUNTIF(Relaciones!$A:$A,B73)
A74: Lo que entra a mano y WhatsApp | B74: respuesta_parada | C74: Respuesta de un operario a una parada que ninguna señal explica (Respuesta de src/entities/pozos.ts): el único dato del libro que entra a mano, marcado como declarado. POST /api/paradas/:evento/respuesta (pantalla) o webhook (WhatsApp); GET /api/paradas/respuestas. Una por evento: la PRIMERA gana (clave primaria → 409). Solo inserción: no se edita ni se reemplaza. | D74: Respuesta (src/entities/pozos.ts) | E74: Persona con causa:declarar o causa:completar (pantalla) o resuelta por el webhook (WhatsApp). | F74: POST /api/paradas/:evento/respuesta GET /api/paradas/respuestas POST /api/webhooks/whatsapp | G74: La primera gana (409); no se edita ni se reemplaza. 403 si el cuerpo trae canal whatsapp: eso solo entra por el webhook. 422: campo del cuerpo distinto al del evento, parte que no es del equipo, bomba sin parte, modo que no es de la parte, texto libre < 8. Si llega después del arranque, la parada es no conformidad. Único: (entrante_meta_id). Solo eventos de pozo o de bomba; el modo es de la parte (u OTH). [trigger respuesta_parada_reglas: INSERT] Solo inserción: UPDATE, DELETE y TRUNCATE rechazados (SQLSTATE 23001). [trigger respuesta_parada_sin_truncate: TRUNCATE] Solo inserción: UPDATE, DELETE y TRUNCATE rechazados (SQLSTATE 23001). [trigger respuesta_parada_solo_insercion: UPDATE DELETE] | H74: =COUNTIF(Columnas!$B:$B,B74) | I74: =COUNTIF(Relaciones!$A:$A,B74)
A75: Lo que entra a mano y WhatsApp | B75: analisis | C75: Análisis de confiabilidad de una falla declarada (Analisis de src/entities/catalogo.ts): mecanismo (ISO 14224 B.2) y causa raíz (B.3). POST /api/analisis/:evento (causa:completar); GET /api/analisis → vigentes (la versión más alta) y anteriores. Un segundo POST es una versión nueva. Solo inserción. | D75: Analisis (src/entities/catalogo.ts) | E75: Persona con causa:completar (confiabilidad, jefe de mantenimiento). | F75: POST /api/analisis/:evento GET /api/analisis | G75: Exige respuesta declarada con parte (422). Un segundo POST es versión nueva; la anterior queda. Exige respuesta con parte; versiones consecutivas. [trigger analisis_reglas: INSERT] Solo inserción: UPDATE, DELETE y TRUNCATE rechazados (SQLSTATE 23001). [trigger analisis_sin_truncate: TRUNCATE] Solo inserción: UPDATE, DELETE y TRUNCATE rechazados (SQLSTATE 23001). [trigger analisis_solo_insercion: UPDATE DELETE] | H75: =COUNTIF(Columnas!$B:$B,B75) | I75: =COUNTIF(Relaciones!$A:$A,B75)
A76: Lo que entra a mano y WhatsApp | B76: folio_contador | C76: Último consecutivo de folio emitido por año. Se incrementa en la misma transacción del informe (siguiente_folio): sin huecos y nunca reutilizado. | E76: Servidor (siguiente_folio). | F76: POST /api/informes | G76: Consecutivo por año, sin huecos, nunca reutilizado. | H76: =COUNTIF(Columnas!$B:$B,B76) | I76: =COUNTIF(Relaciones!$A:$A,B76)
A77: Lo que entra a mano y WhatsApp | B77: informe | C77: Informe exportado con folio y huella (Informe de src/entities/informe.ts). POST /api/informes (evidencia:exportar) registra la CONSULTA; el servidor calcula las cifras con su libro y su versión vigente, la forma canónica y la huella SHA-256. GET /api/informes, /api/informes/:folio y /:folio/verificacion. Solo inserción. | D77: Informe (src/entities/informe.ts) | E77: Servidor, por quien tiene evidencia:exportar y todos los campos del informe. | F77: POST /api/informes GET /api/informes GET /api/informes/:folio GET /api/informes/:folio/verificacion?huella= | G77: Las cifras y la huella las calcula el servidor con su libro y su versión vigente. Solo inserción. Único: (anio, numero). Solo inserción: UPDATE, DELETE y TRUNCATE rechazados (SQLSTATE 23001). [trigger informe_sin_truncate: TRUNCATE] Solo inserción: UPDATE, DELETE y TRUNCATE rechazados (SQLSTATE 23001). [trigger informe_solo_insercion: UPDATE DELETE] | H77: =COUNTIF(Columnas!$B:$B,B77) | I77: =COUNTIF(Relaciones!$A:$A,B77)
A78: Lo que entra a mano y WhatsApp | B78: informe_campo | C78: Campos del informe (ConsultaInforme.campos). GET /api/informes/:folio exige que TODOS sean de la persona. Solo inserción. | D78: ConsultaInforme.campos (src/entities/informe.ts) | E78: Servidor. | F78: GET /api/informes/:folio (403 si un campo no es de la persona) | G78: Solo inserción. Solo inserción: UPDATE, DELETE y TRUNCATE rechazados (SQLSTATE 23001). [trigger informe_campo_sin_truncate: TRUNCATE] Solo inserción: UPDATE, DELETE y TRUNCATE rechazados (SQLSTATE 23001). [trigger informe_campo_solo_insercion: UPDATE DELETE] | H78: =COUNTIF(Columnas!$B:$B,B78) | I78: =COUNTIF(Relaciones!$A:$A,B78)
A79: Lo que entra a mano y WhatsApp | B79: mensaje | C79: Registro de lo que TRIM manda por WhatsApp (Mensaje de src/entities/mensajes.ts). GET /api/mensajes. Se guarda al intentar enviar y no se reescribe: el que salió trae texto (exactamente la plantilla con sus parámetros) y el que no se pudo armar trae no_enviado (el motivo). Cada mensaje se arma con la versión de la configuración que regía a su hora. Solo inserción, salvo poner una vez el id de Meta. | D79: Mensaje (src/entities/mensajes.ts) | E79: Servidor (reglas de mensajes.ts) al enviar por la Cloud API de Meta. | F79: GET /api/mensajes?campos | G79: Se guarda al intentar enviar y no se reescribe; solo se pone una vez el id de Meta. Se arma con la configuración que regía a su hora (configEn). Un parámetro que no sirve deja ESE mensaje con no_enviado; los demás salen. Único: (meta_id). Solo inserción: UPDATE, DELETE y TRUNCATE rechazados (SQLSTATE 23001). [trigger mensaje_sin_truncate: TRUNCATE] Solo inserción; el id de Meta se pone una vez. [trigger mensaje_solo_meta_id: UPDATE DELETE] | H79: =COUNTIF(Columnas!$B:$B,B79) | I79: =COUNTIF(Relaciones!$A:$A,B79)
A80: Lo que entra a mano y WhatsApp | B80: mensaje_libre | C80: Mensajes libres que TRIM manda dentro de la ventana de 24 h que abre la respuesta de la persona (CONTRATO.md, «WhatsApp» y «El webhook»; 5D.5): «¿Qué vio en {parte}?», «¿Qué parte?», «¿Qué fue?», «Escriba qué encontró», «Registrado…», «Ya respondió…» y los rechazos («Ese número no recibe las alertas de este campo…»). No son plantillas y no salen en GET /api/mensajes. Guardan el estado del diálogo: la siguiente respuesta cita su meta_id (context.id) y de aquí salen el evento, la parte y el modo ya escogidos y las opciones válidas; la respuesta_parada se inserta solo con el último paso. Solo inserción, salvo poner una vez el id de Meta. | E80: Servidor, al contestar una respuesta por WhatsApp dentro de la ventana de 24 h (no es plantilla). | F80: POST /api/webhooks/whatsapp (lo que el servidor contesta) | G80: No sale en GET /api/mensajes: es el diálogo, no el registro de avisos. La siguiente respuesta cita su meta_id: de aquí salen evento, parte y modo ya escogidos y las opciones válidas. Dentro de las 24 h del entrante (lo revisa el servidor). Solo inserción, salvo poner una vez el id de Meta. Único: (meta_id). Solo inserción: UPDATE, DELETE y TRUNCATE rechazados (SQLSTATE 23001). [trigger mensaje_libre_sin_truncate: TRUNCATE] Solo inserción; el id de Meta se pone una vez. [trigger mensaje_libre_solo_meta_id: UPDATE DELETE] | H80: =COUNTIF(Columnas!$B:$B,B80) | I80: =COUNTIF(Relaciones!$A:$A,B80)
A81: Lo que entra a mano y WhatsApp | B81: estado_mensaje | C81: Estados de entrega que Meta informa por el webhook (statuses[]): enviado, entregado, leído o fallido, de una plantilla (mensaje) o de un mensaje libre del diálogo (mensaje_libre). Se agregan; el mensaje no se toca. Solo inserción. | E81: Servidor, con los estados que informa Meta. | F81: POST /api/webhooks/whatsapp (statuses[]) | G81: Es de un mensaje o de un mensaje_libre registrado. Solo inserción. El id de Meta es de un mensaje o de un mensaje_libre registrado (hace de clave foránea a las dos). [trigger estado_mensaje_de_saliente: INSERT] Solo inserción: UPDATE, DELETE y TRUNCATE rechazados (SQLSTATE 23001). [trigger estado_mensaje_sin_truncate: TRUNCATE] Solo inserción: UPDATE, DELETE y TRUNCATE rechazados (SQLSTATE 23001). [trigger estado_mensaje_solo_insercion: UPDATE DELETE] | H81: =COUNTIF(Columnas!$B:$B,B81) | I81: =COUNTIF(Relaciones!$A:$A,B81)
A82: Lo que entra a mano y WhatsApp | B82: carga_asignacion | C82: Una carga de la asignación oficial (CargaAsignacion de src/entities/asignacion.ts): quién la subió, cuándo y por qué. POST /api/asignacion-oficial (asignacion:cargar), todo o nada. Solo inserción: un reemplazo no borra el rastro. | D82: CargaAsignacion (src/entities/asignacion.ts) | E82: Persona con asignacion:cargar (producción), o la lectura del sistema de contabilidad de hidrocarburos. | F82: POST /api/asignacion-oficial GET /api/asignacion-oficial → cargas | G82: Todo o nada. Solo inserción: un reemplazo no borra el rastro. Solo inserción: UPDATE, DELETE y TRUNCATE rechazados (SQLSTATE 23001). [trigger carga_asignacion_sin_truncate: TRUNCATE] Solo inserción: UPDATE, DELETE y TRUNCATE rechazados (SQLSTATE 23001). [trigger carga_asignacion_solo_insercion: UPDATE DELETE] | H82: =COUNTIF(Columnas!$B:$B,B82) | I82: =COUNTIF(Relaciones!$A:$A,B82)
A83: Lo que entra a mano y WhatsApp | B83: carga_asignacion_grupo | C83: Cada (mes, campo) que trajo una carga (CargaAsignacion.grupos): cuántos pozos entraron y cuántos tenía la carga que reemplazó (0 si no había). | D83: CargaAsignacion.grupos (src/entities/asignacion.ts) | E83: Servidor, en la transacción de la carga. | F83: GET /api/asignacion-oficial → cargas[].grupos | G83: Solo meses cerrados (422). Solo inserción. Solo inserción: UPDATE, DELETE y TRUNCATE rechazados (SQLSTATE 23001). [trigger carga_asignacion_grupo_sin_truncate: TRUNCATE] Solo inserción: UPDATE, DELETE y TRUNCATE rechazados (SQLSTATE 23001). [trigger carga_asignacion_grupo_solo_insercion: UPDATE DELETE] | H83: =COUNTIF(Columnas!$B:$B,B83) | I83: =COUNTIF(Relaciones!$A:$A,B83)
A84: Lo que entra a mano y WhatsApp | B84: asignacion_oficial | C84: Filas de la asignación oficial que reportó la operadora, pozo por pozo (FilaCargada de src/entities/asignacion.ts), con la carga que las trajo. Lo que rige en un (mes, campo) son las filas de su carga más reciente (v_asignacion_oficial); las anteriores quedan como rastro. Sin FK a pozo: un pozo que TRIM no tiene se muestra como dato inválido, no se rechaza. | D84: FilaCargada (src/entities/asignacion.ts) | E84: Servidor, en la transacción de la carga. | F84: POST /api/asignacion-oficial GET /api/asignacion-oficial → filas cotejo con GET /api/vistas/asignacion | G84: Rige la carga más reciente de cada (mes, campo). bbl ≥ 0; horas de 0 a días del mes × 24 (422). Solo inserción. El cotejo no cambia el libro. Solo inserción: UPDATE, DELETE y TRUNCATE rechazados (SQLSTATE 23001). [trigger asignacion_oficial_sin_truncate: TRUNCATE] Solo inserción: UPDATE, DELETE y TRUNCATE rechazados (SQLSTATE 23001). [trigger asignacion_oficial_solo_insercion: UPDATE DELETE] | H84: =COUNTIF(Columnas!$B:$B,B84) | I84: =COUNTIF(Relaciones!$A:$A,B84)
A85: Lo que entra a mano y WhatsApp | B85: cambio_planta | C85: Historial del esquema de planta (CambioPlanta de src/entities/planta.ts). POST /api/planta/cambios manda la operación (CambioDePlanta) y el servidor la aplica con aplicarCambioPlanta sobre su planta; GET /api/planta/cambios. Solo inserción. | D85: CambioPlanta (src/entities/planta.ts) | E85: Persona con conector:configurar y el campo. | F85: POST /api/planta/cambios GET /api/planta/cambios | G85: Se manda la operación, no la planta; el servidor la aplica sobre la suya. Solo inserción. Solo inserción: UPDATE, DELETE y TRUNCATE rechazados (SQLSTATE 23001). [trigger cambio_planta_sin_truncate: TRUNCATE] Solo inserción: UPDATE, DELETE y TRUNCATE rechazados (SQLSTATE 23001). [trigger cambio_planta_solo_insercion: UPDATE DELETE] | H85: =COUNTIF(Columnas!$B:$B,B85) | I85: =COUNTIF(Relaciones!$A:$A,B85)
A86: Precálculo de meses cerrados | B86: factor_asignacion_mes | C86: Factor de asignación de un campo en un mes cerrado: FA = R/T con solo los días con dato fiscal (FilaFA de src/entities/libro.ts, más R y T). Va en Libro.fa y en el panel de medición oficial. | D86: FilaFA (src/entities/libro.ts) + R y T | E86: Servidor (trabajo de precálculo al cerrarse y publicarse el mes). | F86: GET /api/vistas/diferidos → fa GET /api/vistas/diferidos/mensual | G86: No se actualiza en sitio: el mes se recalcula entero y se anota en recalculo_mes. No se actualiza en sitio: el mes se recalcula (borrar e insertar) y se anota en recalculo_mes. [trigger factor_asignacion_mes_sin_update: UPDATE] | H86: =COUNTIF(Columnas!$B:$B,B86) | I86: =COUNTIF(Relaciones!$A:$A,B86)
A87: Precálculo de meses cerrados | B87: libro_mes | C87: El libro de un campo en un mes cerrado y publicado (Libro de src/entities/libro.ts sin tramos, porPozo, preguntas ni custodia detallada; la fila de GET /api/vistas/diferidos/mensual). El portafolio se arma sumando barriles por campo (tolerancia en cuadratura entre campos; pe y tasas recalculados). huella_cifras = SHA-256 de la forma canónica de informe.ts para ese campo y mes: si un recálculo la cambia, cambiaron los insumos. | D87: Libro sin tramos (src/entities/libro.ts); MesLibro.libro | E87: Servidor (precálculo). | F87: GET /api/vistas/diferidos/mensual GET /api/vistas/diferidos (meses cerrados) GET /api/vistas/diferidos/base | G87: Solo meses cerrados y publicados por el campo. Las cifras de barriles no cambian; una respuesta tardía cambia la clasificación y obliga a recalcular el mes. No se actualiza en sitio: el mes se recalcula (borrar e insertar) y se anota en recalculo_mes. [trigger libro_mes_sin_update: UPDATE] | H87: =COUNTIF(Columnas!$B:$B,B87) | I87: =COUNTIF(Relaciones!$A:$A,B87)
A88: Precálculo de meses cerrados | B88: tramo_diferido | C88: Lo que costó un evento de pozo, partido por día (un Tramo de src/entities/libro.ts recortado a cada día: cambian la prueba vigente y el FA). Sumar los días de un período da sus tramos (aditividad). Solo meses cerrados y publicados; el mes en curso se calcula en vivo. | D88: Tramo partido por día (src/entities/libro.ts) | E88: Servidor (precálculo). | F88: GET /api/vistas/diferidos → tramos (meses cerrados) GET /api/vistas/pozos… GET /api/vistas/equipos/:campo/:equipo/ficha | G88: Σ de los días de un mes = diferido del libro del mes. No se actualiza en sitio: el mes se recalcula (borrar e insertar) y se anota en recalculo_mes. [trigger tramo_diferido_sin_update: UPDATE] | H88: =COUNTIF(Columnas!$B:$B,B88) | I88: =COUNTIF(Relaciones!$A:$A,B88)
A89: Precálculo de meses cerrados | B89: asignacion_pozo_mes | C89: Lo que TRIM asigna a cada pozo en un mes cerrado (AsignacionPozo de src/entities/libro.ts): lo real del PMO repartido por prueba × FA × horas abierto. GET /api/vistas/asignacion?campo&mes; se coteja con la oficial. Σ asignado = real del campo. | D89: AsignacionPozo (src/entities/libro.ts) | E89: Servidor (precálculo). | F89: GET /api/vistas/asignacion?campo&mes | G89: Σ asignado = real del campo en el mes. No se actualiza en sitio: el mes se recalcula (borrar e insertar) y se anota en recalculo_mes. [trigger asignacion_pozo_mes_sin_update: UPDATE] | H89: =COUNTIF(Columnas!$B:$B,B89) | I89: =COUNTIF(Relaciones!$A:$A,B89)
A90: Precálculo de meses cerrados | B90: recalculo_mes | C90: Bitácora del precálculo: cada vez que se (re)calcula un mes de un campo, por qué y si cambiaron las cifras protegidas (huella). Una huella distinta en un mes publicado es un incidente: cambiaron los insumos. Solo inserción. | E90: Servidor. | F90: (auditoría del precálculo) | G90: Una huella distinta en un mes publicado es un incidente. Solo inserción. Solo inserción: UPDATE, DELETE y TRUNCATE rechazados (SQLSTATE 23001). [trigger recalculo_mes_sin_truncate: TRUNCATE] Solo inserción: UPDATE, DELETE y TRUNCATE rechazados (SQLSTATE 23001). [trigger recalculo_mes_solo_insercion: UPDATE DELETE] | H90: =COUNTIF(Columnas!$B:$B,B90) | I90: =COUNTIF(Relaciones!$A:$A,B90)
A91: Cadena de datos | B91: v_procedencia | C91: GET /api/campos/:campo/tags/:tag/procedencia: instrumento, lectura, calculo, custodia y (solo con conector:configurar) tecnico. Las frases las escribe el front (cadena.ts). 404 tag-no-registrado si no hay fila. | D91: respuesta de GET …/procedencia | E91: (vista) | F91: GET /api/campos/:campo/tags/:tag/procedencia | G91: tecnico solo con conector:configurar (lo decide el servidor). | H91: =COUNTIF(Columnas!$B:$B,B91) | I91: =COUNTIF(Relaciones!$A:$A,B91)
A92: Insumos del motor | B92: v_limite_tag | C92: catalogo.campos[c].limites (LimiteTag de src/entities/limites.ts): la única fuente de la banda normal (registro de tags) y de la alarma (base maestra). normal con null del lado abierto; sin alarma, el vigía dice «sin límite». | D92: LimiteTag (src/entities/limites.ts) | E92: (vista) | F92: GET /api/catalogo → campos[c].limites | H92: =COUNTIF(Columnas!$B:$B,B92) | I92: =COUNTIF(Relaciones!$A:$A,B92)
A93: Insumos del motor | B93: v_produccion_mes | C93: ProduccionMes por campo y mes: dias[] con NULL donde no hay dato del computador de flujo (nunca 0), hasta el día de hoy en el mes en curso. Base de GET /api/campos/:campo/produccion-diaria. | D93: ProduccionMes (src/entities/pozos.ts) | E93: (vista) | F93: GET /api/campos/:campo/produccion-diaria | H93: =COUNTIF(Columnas!$B:$B,B93) | I93: =COUNTIF(Relaciones!$A:$A,B93)
A94: Insumos del motor | B94: v_calendario | C94: catalogo.calendario (Mes de src/entities/libro.ts): desde y hasta del mes (el de hoy termina ahora) y publicado en TODOS los campos con fiscal. | D94: Mes (src/entities/libro.ts) | E94: (vista) | F94: GET /api/catalogo → calendario | H94: =COUNTIF(Columnas!$B:$B,B94) | I94: =COUNTIF(Relaciones!$A:$A,B94)
A95: Lo que entra a mano y WhatsApp | B95: v_analisis_vigente | C95: GET /api/analisis → vigentes: la última versión de cada evento. Las demás son anteriores. | D95: Analisis (vigentes) | E95: (vista) | F95: GET /api/analisis → vigentes | H95: =COUNTIF(Columnas!$B:$B,B95) | I95: =COUNTIF(Relaciones!$A:$A,B95)
A96: Lo que entra a mano y WhatsApp | B96: v_asignacion_oficial | C96: GET /api/asignacion-oficial → filas (FilaCargada): lo que rige en cada (mes, campo) = las filas de su carga más reciente. | D96: FilaCargada (vigente) | E96: (vista) | F96: GET /api/asignacion-oficial → filas | H96: =COUNTIF(Columnas!$B:$B,B96) | I96: =COUNTIF(Relaciones!$A:$A,B96)
A97: Lo que se lee de SAP PM | B97: v_orden_sap | C97: GET /api/sap/ordenes (OrdenSap): la clase de TRIM mapeada y los repuestos de la orden. | D97: OrdenSap | E97: (vista) | F97: GET /api/sap/ordenes | H97: =COUNTIF(Columnas!$B:$B,B97) | I97: =COUNTIF(Relaciones!$A:$A,B97)
A98: Personas | B98: v_usuario | C98: Usuario con campos: NULL = "todos", si no la lista. La forma mínima (PersonaVisible) la recorta la API según quién pregunta. | D98: Usuario | E98: (vista) | F98: GET /api/usuarios | H98: =COUNTIF(Columnas!$B:$B,B98) | I98: =COUNTIF(Relaciones!$A:$A,B98)
A99: Personas | B99: v_capacidades_rol | C99: Capacidades efectivas de cada rol, con lo que cada una incluye (puedeHacer de tipos.ts): las de GET /api/sesion. | D99: puedeHacer (src/entities/tipos.ts) | E99: (vista) | F99: GET /api/sesion → capacidades | H99: =COUNTIF(Columnas!$B:$B,B99) | I99: =COUNTIF(Relaciones!$A:$A,B99)

Sheet Columnas
A1: Grupo | B1: Tabla | C1: Columna | D1: Tipo | E1: Nulo | F1: PK | G1: FK (tabla.columna) | H1: Único | I1: CHECK | J1: Descripción | K1: Ejemplo
A2: Registro de campos y planta | B2: campo | C2: id | D2: text | E2: no | F2: sí | I2: CHECK (((btrim(id) <> ''::text) AND (id = btrim(id)))) | J2: Id del campo: único, no vacío y sin espacios en los bordes (ceiba, morichal…). Es la clave que usan todas las demás tablas. | K2: ceiba
A3: Registro de campos y planta | B3: campo | C3: nombre | D3: text | E3: no | I3: CHECK ((btrim(nombre) <> ''::text)) | J3: Nombre para leer (La Ceiba). | K3: La Ceiba
A4: Registro de campos y planta | B4: campo | C4: cuenca | D4: text | E4: no | J4: Cuenca sedimentaria (Magdalena Medio, Llanos, Putumayo…). | K4: Llanos
A5: Registro de campos y planta | B5: campo | C5: choke | D5: text | E5: no | I5: CHECK ((choke = ANY (ARRAY['Pozos'::text, 'Planta'::text, 'Evacuación'::text, 'Mercado'::text]))) | J5: Qué limita al campo, dicho por la operación: Pozos, Planta, Evacuación o Mercado. Descriptivo. | K5: Planta
A6: Registro de campos y planta | B6: campo | C6: nota | D6: text | E6: no | J6: Nota libre del registro. | K6: Tres bombas de agua en paralelo, sin reserva: si para una, se cierran pozos.
A7: Registro de campos y planta | B7: activo | C7: campo_id | D7: text | E7: no | F7: sí | G7: campo.id | H7: único con (campo_id, codigo, clase) | J7: Campo del activo. | K7: ceiba
A8: Registro de campos y planta | B8: activo | C8: codigo | D8: text | E8: no | F8: sí | H8: único con (campo_id, codigo, clase) | I8: CHECK ((btrim(codigo) <> ''::text)) | J8: Código del activo en el campo (P-201B, K-101, LC-14). | K8: C-401
A9: Registro de campos y planta | B9: activo | C9: clase | D9: text | E9: no | H9: único con (campo_id, codigo, clase) | I9: CHECK ((clase = ANY (ARRAY['catalogo'::text, 'pozo'::text]))) | J9: catalogo (equipo de superficie del registro de ingeniería) o pozo. | K9: catalogo
A10: Registro de campos y planta | B10: equipo | C10: campo_id | D10: text | E10: no | F10: sí | G10: activo.campo_id | J10: Campo. | K10: ceiba
A11: Registro de campos y planta | B11: equipo | C11: codigo | D11: text | E11: no | F11: sí | G11: activo.codigo | J11: Código del equipo (P-201B). | K11: C-401
A12: Registro de campos y planta | B12: equipo | C12: clase | D12: text | E12: no | G12: activo.clase | I12: CHECK ((clase = 'catalogo'::text)) | J12: Siempre catalogo: amarra la fila al supertipo activo. | K12: catalogo
A13: Registro de campos y planta | B13: equipo | C13: nombre | D13: text | E13: no | I13: CHECK ((btrim(nombre) <> ''::text)) | J13: Nombre del equipo. | K13: Compresor de gas
A14: Registro de campos y planta | B14: equipo | C14: sistema | D14: text | E14: no | J14: Sistema al que pertenece (Tratamiento de agua, Servicios industriales…). | K14: Compresión
A15: Registro de campos y planta | B15: equipo | C15: clase_iso | D15: text | E15: no | I15: CHECK ((btrim(clase_iso) <> ''::text)) | J15: Clase de equipo de la taxonomía ISO 14224 (bomba-centrifuga, compresor-aire, unidad-lact…). De ella y del papel de la bomba sale el catálogo de daños (clase_iso_catalogo). | K15: compresor-gas
A16: Registro de campos y planta | B16: equipo | C16: criticidad | D16: smallint | E16: no | I16: CHECK (((criticidad >= 1) AND (criticidad <= 5))) | J16: Criticidad 1 a 5 del registro del cliente. | K16: 4
A17: Registro de campos y planta | B17: equipo | C17: servicio | D17: text | E17: sí | I17: CHECK ((servicio = ANY (ARRAY['aire'::text, 'energia'::text, 'compresion'::text, 'evacuacion'::text, 'proceso'::text, 'tratamiento'::text]))) | J17: Si al caer apaga pozos: el tipo de causa que se le carga (aire, energia, compresion, evacuacion, proceso, tratamiento). NULL si no es un servicio. | K17: compresion
A18: Registro de campos y planta | B18: equipo | C18: modo_falla | D18: text | E18: sí | J18: Modo de falla dominante de la familia, para leer. | K18: Válvulas de succión y descarga ≈ 50,7 %
A19: Registro de campos y planta | B19: equipo | C19: norma | D19: text | E19: sí | J19: Norma o referencia técnica que rige la vigilancia del equipo. | K19: El modo de falla #1 de la familia NO es monitoreable a nuestra resolución: se diagnostica por ángulo de cigüeñal.
A20: Registro de campos y planta | B20: equipo | C20: intervencion_ubicacion | D20: text | E20: sí | I20: CHECK ((((intervencion_ubicacion IS NULL) = (intervencion_accion IS NULL)) AND ((intervencion_accion IS NULL) = (intervencion_avisar_a IS NULL)))) | J20: Dónde está, para ir al equipo (Equipo.intervencion.ubicacion). Es de ESTE campo. | K20: Batería 1 · tren de gas
A21: Registro de campos y planta | B21: equipo | C21: intervencion_accion | D21: text | E21: sí | I21: CHECK ((((intervencion_ubicacion IS NULL) = (intervencion_accion IS NULL)) AND ((intervencion_accion IS NULL) = (intervencion_avisar_a IS NULL)))) | J21: Acción inmediata (Equipo.intervencion.accionInmediata). | K21: Ante parada súbita, verificar presión de descarga y temperatura por etapa antes de reponer: el modo dominante no avisa.
A22: Registro de campos y planta | B22: equipo | C22: intervencion_avisar_a | D22: text | E22: sí | I22: CHECK ((((intervencion_ubicacion IS NULL) = (intervencion_accion IS NULL)) AND ((intervencion_accion IS NULL) = (intervencion_avisar_a IS NULL)))) | J22: A quién avisar (Equipo.intervencion.avisarA). | K22: Supervisor de operaciones
A23: Registro de campos y planta | B23: equipo | C23: distribucion_falla | D23: jsonb | E23: sí | J23: Reparto de modos de falla de la familia con su fuente bibliográfica: {"reparto":[["Mecánicas",44.1],…],"fuente":"…"} (Equipo.distribucionFalla). | K23: {'fuente': '21 compresores de pistón a lo largo de 20 años. Succión y descarga suman 50,7 %: es el modo de falla #1 de la familia.', 'reparto': [['Válvulas de succión', 29.1], ['Válvulas de descarga', 21.6], ['Resto de elementos', 49.3]]}
A24: Registro de campos y planta | B24: equipo | C24: aguas_abajo | D24: text | E24: sí | I24: CHECK ((btrim(aguas_abajo) <> ''::text)) | J24: Lo que queda sin servicio si el equipo para, como lo declara el registro del campo (Equipo.aguasAbajo: «todo el campo», «4 pozos», «tren de gas», «sin impacto»). El motor lo compara: un servicio en alarma con «todo el campo» entra en el riesgo de ahora. NULL en las bombas de la línea: ahí lo dice el respaldo firmado (respaldoEnCampo de equipos.ts), y en una bomba sin perfil en el campo la API dice «sin declarar en este campo». | K24: tren de gas
A25: Registro de campos y planta | B25: equipo | C25: redundancia | D25: text | E25: sí | I25: CHECK ((btrim(redundancia) <> ''::text)) | J25: Respaldo del equipo en el campo, para leer (Equipo.redundancia: «3 unidades (N+1)», «respaldo en línea (H-301)», «sin respaldo»). NULL en las bombas de la línea: lo dice el respaldo firmado (respaldo.detalle, o «sin respaldo» con libre_bpd = 0). | K25: sin respaldo
A26: Registro de campos y planta | B26: planta_campo | C26: campo_id | D26: text | E26: no | F26: sí | G26: campo.id | J26: Campo. | K26: ceiba
A27: Registro de campos y planta | B27: planta_campo | C27: crudo_bpd | D27: numeric | E27: no | I27: CHECK ((crudo_bpd >= (0)::numeric)) | J27: Caudales.crudo: crudo que mueve la planta, bbl/d. | K27: 10450
A28: Registro de campos y planta | B28: planta_campo | C28: crudo_cap_bpd | D28: numeric | E28: no | I28: CHECK ((crudo_cap_bpd >= (0)::numeric)) | J28: Caudales.crudoCap: capacidad del tren de crudo, bbl/d. | K28: 12000
A29: Registro de campos y planta | B29: planta_campo | C29: agua_bpd | D29: numeric | E29: no | I29: CHECK ((agua_bpd >= (0)::numeric)) | J29: Caudales.agua: agua producida, bbl/d. | K29: 224200
A30: Registro de campos y planta | B30: planta_campo | C30: agua_cap_bpd | D30: numeric | E30: no | I30: CHECK ((agua_cap_bpd >= (0)::numeric)) | J30: Caudales.aguaCap: capacidad del tren de agua, bbl/d. | K30: 267750
A31: Registro de campos y planta | B31: planta_campo | C31: gas_bpd | D31: numeric | E31: no | I31: CHECK ((gas_bpd >= (0)::numeric)) | J31: Caudales.gas, en la unidad del tren de gas. | K31: 3850
A32: Registro de campos y planta | B32: planta_campo | C32: gas_cap_bpd | D32: numeric | E32: no | I32: CHECK ((gas_cap_bpd >= (0)::numeric)) | J32: Caudales.gasCap. 0 = el campo no tiene tren de gas. | K32: 4200
A33: Registro de campos y planta | B33: planta_campo | C33: choke_pozos | D33: numeric | E33: no | J33: Chokes.pozos (modelo NSTA/SPE). | K33: 12500
A34: Registro de campos y planta | B34: planta_campo | C34: choke_planta | D34: numeric | E34: no | J34: Chokes.planta. | K34: 11800
A35: Registro de campos y planta | B35: planta_campo | C35: choke_evacuacion | D35: numeric | E35: no | J35: Chokes.evacuacion. | K35: 14000
A36: Registro de campos y planta | B36: planta_campo | C36: choke_mercado | D36: numeric | E36: no | J36: Chokes.mercado. | K36: 15000
A37: Registro de campos y planta | B37: planta_campo | C37: nota | D37: text | E37: no | J37: PlantaCampo.nota. | K37: El agua (95 % de lo que sale de los pozos) la sacan tres bombas en paralelo, P-201A, B y C, de 90.000 bbl/d de placa; el cabezal de disposición las limita a unos 89.250 cada una. Si para una, las otras dos no alcanzan: el tanque se llena en un par de horas y hay que cerrar parte de los pozos. Es el cuello de botella del campo.
A38: Registro de campos y planta | B38: planta_elemento | C38: campo_id | D38: text | E38: no | F38: sí | G38: activo.campo_id · planta_campo.campo_id | H38: único con (campo_id, tren, orden) | J38: Campo. | K38: ceiba
A39: Registro de campos y planta | B39: planta_elemento | C39: id | D39: text | E39: no | F39: sí | I39: CHECK ((btrim(id) <> ''::text)) | J39: Id del elemento. Un id identifica una sola cosa en el campo: no se repite entre elementos ni miembros (trigger planta_id_unico). | K39: aire
A40: Registro de campos y planta | B40: planta_elemento | C40: tren | D40: text | E40: no | H40: único con (campo_id, tren, orden) | I40: CHECK ((tren = ANY (ARRAY['tronco'::text, 'gas'::text, 'crudo'::text, 'agua'::text, 'servicios'::text]))) | J40: Tren: tronco, gas, crudo, agua o servicios. | K40: servicios
A41: Registro de campos y planta | B41: planta_elemento | C41: orden | D41: smallint | E41: no | H41: único con (campo_id, tren, orden) | I41: CHECK ((orden >= 0)) | J41: Posición dentro del tren (0 primero). | K41: 1
A42: Registro de campos y planta | B42: planta_elemento | C42: simbolo | D42: text | E42: no | I42: CHECK ((simbolo = ANY (ARRAY['pozos'::text, 'manifold'::text, 'separador'::text, 'depurador'::text, 'tratador'::text, 'tanque'::text, 'medicion'::text, 'compresor'::text, 'bomba'::text, 'inyeccion'::text, 'tea'::text, 'subestacion'::text, 'aire'::text, 'salida'::text]))) | J42: Símbolo del dibujo (Simbolo). | K42: aire
A43: Registro de campos y planta | B43: planta_elemento | C43: etiqueta | D43: text | E43: no | J43: Texto del elemento. | K43: Aire de instrumentos
A44: Registro de campos y planta | B44: planta_elemento | C44: equipo | D44: text | E44: sí | G44: activo.codigo | J44: Activo del campo que representa. NULL = configurado pero sin instrumentar. | K44: K-101
A45: Registro de campos y planta | B45: planta_elemento | C45: pie | D45: text | E45: sí | J45: Texto al pie. | K45: proceso
A46: Registro de campos y planta | B46: planta_elemento | C46: nivel_tag | D46: text | E46: sí | I46: CHECK (((nivel_tag IS NULL) = (nivel_tope IS NULL))) | J46: nivelDe.tag: tag de nivel que se pinta en el símbolo.
A47: Registro de campos y planta | B47: planta_elemento | C47: nivel_tope | D47: double precision | E47: sí | I47: CHECK (((nivel_tag IS NULL) = (nivel_tope IS NULL))) | J47: nivelDe.tope: valor que llena el símbolo.
A48: Registro de campos y planta | B48: planta_elemento | C48: fluido | D48: text | E48: sí | I48: CHECK ((fluido = ANY (ARRAY['multi'::text, 'crudo'::text, 'gas'::text, 'agua'::text, 'elec'::text, 'aire'::text]))) | J48: Corriente que lleva (Corriente).
A49: Registro de campos y planta | B49: planta_elemento | C49: pmo | D49: text | E49: sí | J49: Si es punto de medición oficial, su código (PMO-02): cambia quién lo puede tocar.
A50: Registro de campos y planta | B50: planta_elemento | C50: rama | D50: boolean | E50: no | J50: Cuelga del anterior y no continúa la cadena (la tea). | K50: False
A51: Registro de campos y planta | B51: planta_elemento | C51: restantes_cuantos | D51: integer | E51: sí | I51: CHECK (((restantes_cuantos IS NULL) = (restantes_etiqueta IS NULL))) · CHECK ((restantes_cuantos >= 0)) | J51: restantes.cuantos: miembros configurados que no se dibujan uno a uno.
A52: Registro de campos y planta | B52: planta_elemento | C52: restantes_etiqueta | D52: text | E52: sí | I52: CHECK (((restantes_cuantos IS NULL) = (restantes_etiqueta IS NULL))) | J52: restantes.etiqueta.
A53: Registro de campos y planta | B53: planta_miembro | C53: campo_id | D53: text | E53: no | F53: sí | G53: planta_elemento.campo_id · activo.campo_id | H53: único con (campo_id, elemento_id, orden) | J53: Campo. | K53: ceiba
A54: Registro de campos y planta | B54: planta_miembro | C54: elemento_id | D54: text | E54: no | G54: planta_elemento.id | H54: único con (campo_id, elemento_id, orden) | J54: Elemento (grupo) al que pertenece. | K54: pozos
A55: Registro de campos y planta | B55: planta_miembro | C55: id | D55: text | E55: no | F55: sí | I55: CHECK ((btrim(id) <> ''::text)) | J55: Id del miembro, único en el campo junto con los de los elementos. | K55: LC-09
A56: Registro de campos y planta | B56: planta_miembro | C56: orden | D56: smallint | E56: no | H56: único con (campo_id, elemento_id, orden) | I56: CHECK ((orden >= 0)) | J56: Posición dentro del grupo. | K56: 1
A57: Registro de campos y planta | B57: planta_miembro | C57: etiqueta | D57: text | E57: no | J57: Texto del miembro. | K57: LC-09 · ESP
A58: Registro de campos y planta | B58: planta_miembro | C58: equipo | D58: text | E58: sí | G58: activo.codigo | J58: Activo que representa (un pozo o un equipo). NULL = sin instrumentar. | K58: LC-09
A59: Registro de campos y planta | B59: planta_miembro | C59: pie | D59: text | E59: sí | J59: Texto al pie.
A60: Registro de campos y planta | B60: planta_miembro | C60: nivel_tag | D60: text | E60: sí | I60: CHECK (((nivel_tag IS NULL) = (nivel_tope IS NULL))) | J60: nivelDe.tag.
A61: Registro de campos y planta | B61: planta_miembro | C61: nivel_tope | D61: double precision | E61: sí | I61: CHECK (((nivel_tag IS NULL) = (nivel_tope IS NULL))) | J61: nivelDe.tope.
A62: Registro de campos y planta | B62: planta_miembro | C62: fluido | D62: text | E62: sí | I62: CHECK ((fluido = ANY (ARRAY['multi'::text, 'crudo'::text, 'gas'::text, 'agua'::text, 'elec'::text, 'aire'::text]))) | J62: Corriente.
A63: Registro de campos y planta | B63: planta_miembro | C63: pmo | D63: text | E63: sí | J63: Código del punto de medición oficial, si lo es.
A64: Cadena de datos | B64: gateway | C64: id | D64: text | E64: no | F64: sí | H64: único con (id, campo_id) | I64: CHECK ((btrim(id) <> ''::text)) | J64: Id del gateway (EPIC-CEIBA-01). En producción sale del certificado de cliente, nunca del cuerpo. | K64: EPIC-CEIBA-01
A65: Cadena de datos | B65: gateway | C65: campo_id | D65: text | E65: no | G65: campo.id | H65: único con (id, campo_id) | J65: Campo donde se inscribió. Los tags que publica son de este campo (FK compuesta en fuente/dispositivo/tag). | K65: ceiba
A66: Cadena de datos | B66: gateway | C66: modelo | D66: text | E66: sí | J66: Modelo del equipo (GRV-EPIC-PR1). | K66: GRV-EPIC-PR1
A67: Cadena de datos | B67: gateway | C67: serie | D67: text | E67: sí | J67: Número de serie. | K67: GRVCEI0016
A68: Cadena de datos | B68: gateway | C68: firmware | D68: text | E68: sí | J68: Versión de firmware declarada en el NBIRTH. | K68: 3.6.2
A69: Cadena de datos | B69: gateway | C69: enlace | D69: text | E69: sí | J69: Enlace de comunicaciones: starlink, fibra, lte… | K69: starlink
A70: Cadena de datos | B70: gateway | C70: buffer_h | D70: numeric | E70: sí | I70: CHECK ((buffer_h > (0)::numeric)) | J70: Autonomía de la cola local (store-and-forward), horas: cuánto aguanta sin enlace sin perder datos. | K70: 48
A71: Cadena de datos | B71: gateway | C71: certificado_huella | D71: text | E71: sí | I71: CHECK ((certificado_huella ~ '^[0-9a-f]{64}$'::text)) | J71: SHA-256 (hex) del certificado de cliente con que se autentica por TLS. NULL en el simulador, que no tiene certificados.
A72: Cadena de datos | B72: gateway | C72: primer_visto | D72: timestamp with time zone | E72: no | I72: CHECK ((ultimo_visto >= primer_visto)) | J72: Primer nacimiento recibido. | K72: 2026-10-02T19:00:00+00:00
A73: Cadena de datos | B73: gateway | C73: ultimo_visto | D73: timestamp with time zone | E73: no | I73: CHECK ((ultimo_visto >= primer_visto)) | J73: Último nacimiento o mensaje recibido. | K73: 2026-10-02T19:00:00+00:00
A74: Cadena de datos | B74: inscripcion | C74: id | D74: bigint | E74: no | F74: sí | J74: Consecutivo.
A75: Cadena de datos | B75: inscripcion | C75: campo_id | D75: text | E75: no | G75: campo.id | J75: Campo para el que se emitió: el gateway que lo canjea queda de este campo.
A76: Cadena de datos | B76: inscripcion | C76: codigo_huella | D76: text | E76: no | H76: único | I76: CHECK ((codigo_huella ~ '^[0-9a-f]{64}$'::text)) | J76: SHA-256 (hex) del código entregado (KEV4Y-SQCMN). El código en claro solo viaja en la respuesta.
A77: Cadena de datos | B77: inscripcion | C77: emitido | D77: timestamp with time zone | E77: no | I77: CHECK ((expira > emitido)) | J77: Hora de emisión.
A78: Cadena de datos | B78: inscripcion | C78: expira | D78: timestamp with time zone | E78: no | I78: CHECK ((expira > emitido)) | J78: Vence (24 h después en el contrato).
A79: Cadena de datos | B79: inscripcion | C79: emitido_por | D79: text | E79: no | G79: usuario.id | J79: Id de la persona que lo pidió (del token; capacidad conector:configurar).
A80: Cadena de datos | B80: inscripcion | C80: canjeado | D80: timestamp with time zone | E80: sí | I80: CHECK (((canjeado IS NULL) = (gateway_id IS NULL))) | J80: Cuándo se canjeó; NULL = sin usar.
A81: Cadena de datos | B81: inscripcion | C81: gateway_id | D81: text | E81: sí | G81: gateway.id | I81: CHECK (((canjeado IS NULL) = (gateway_id IS NULL))) | J81: Gateway que lo canjeó.
A82: Cadena de datos | B82: nacimiento | C82: id | D82: bigint | E82: no | F82: sí | J82: Consecutivo. | K82: 1
A83: Cadena de datos | B83: nacimiento | C83: gateway_id | D83: text | E83: no | G83: gateway.id | J83: Gateway que nació. | K83: EPIC-CEIBA-02
A84: Cadena de datos | B84: nacimiento | C84: campo_id | D84: text | E84: no | G84: campo.id | J84: Campo (del certificado). | K84: ceiba
A85: Cadena de datos | B85: nacimiento | C85: recibido | D85: timestamp with time zone | E85: no | J85: Hora del servidor al aceptarlo. | K85: 2026-10-02T19:00:00+00:00
A86: Cadena de datos | B86: nacimiento | C86: bd_seq | D86: integer | E86: sí | I86: CHECK (((bd_seq >= 0) AND (bd_seq <= 255))) | J86: bdSeq de Sparkplug B (0–255): empareja el NBIRTH con su NDEATH.
A87: Cadena de datos | B87: nacimiento | C87: tags | D87: integer | E87: no | I87: CHECK (((pendientes >= 0) AND (pendientes <= tags))) · CHECK ((tags >= 0)) | J87: Tags declarados en el nacimiento. | K87: 3
A88: Cadena de datos | B88: nacimiento | C88: pendientes | D88: integer | E88: no | I88: CHECK (((pendientes >= 0) AND (pendientes <= tags))) | J88: Tags que quedaron sin equipo (origen_mapeo = pendiente). | K88: 3
A89: Cadena de datos | B89: nacimiento | C89: carga | D89: jsonb | E89: no | J89: El certificado de nacimiento tal como llegó (forma del contrato: campo, gateway, dispositivos[]). | K89: {'campo': 'ceiba', 'gateway': {'id': 'EPIC-CEIBA-02', 'serie': 'GRVCEI9003', 'enlace': 'starlink', 'modelo': 'GRV-EPIC-PR1', 'bufferH': 48, 'firmware': '3.6.0'}, 'dispositivos': [{'fuente': {'reloj': 'el PLC del skid', 'endpoint': 'opc.tcp://skid-ceiba.ot.local:4840', 'protocolo': 'opc-ua'}, 'nombre': 'SKID-AMPLIACION', 'metricas': [{'alto': 65, 'bajo': 35, 'tipo': 'Nivel de interfase', 'clase': 'continua', 'limite': '35 – 65', 'nombre': 'XI-1017', 'unidad': '%', 'cadenciaS': 5}, {'alto': 8, 'bajo': None, 'tipo': 'Presión diferencial', 'clase': 'continua', 'limite': '< 8', 'nombre': 'XT-1017', 'unidad': 'psi', 'cadenciaS': 5}, {'alto': 1250, 'bajo': 1050, 'tipo': 'Presión de descarga', 'clase': 'continua', 'limite': '1.050 – 1.250', 'nombre': 'XP-4016', 'unidad': 'psi', 'cadenciaS': 5}]}]}
A90: Cadena de datos | B90: rechazo | C90: id | D90: bigint | E90: no | F90: sí | J90: Consecutivo.
A91: Cadena de datos | B91: rechazo | C91: cuando | D91: timestamp with time zone | E91: no | J91: Hora del rechazo.
A92: Cadena de datos | B92: rechazo | C92: gateway_id | D92: text | E92: sí | J92: Gateway que se presentó (como lo dijo).
A93: Cadena de datos | B93: rechazo | C93: campo_id | D93: text | E93: sí | J93: Campo con que se presentó.
A94: Cadena de datos | B94: rechazo | C94: codigo | D94: text | E94: no | I94: CHECK ((codigo = ANY (ARRAY['gateway-de-otro-campo'::text, 'tag-de-otro-gateway'::text, 'campo-desconocido'::text, 'nacimiento-mal-formado'::text, 'certificado-invalido'::text]))) | J94: Código del error devuelto (403 gateway-de-otro-campo, 409 tag-de-otro-gateway, 404 campo-desconocido, 400 nacimiento mal formado, certificado inválido).
A95: Cadena de datos | B95: rechazo | C95: motivo | D95: text | E95: no | J95: Mensaje completo.
A96: Cadena de datos | B96: rechazo | C96: tags | D96: text[] | E96: sí | J96: Con tag-de-otro-gateway: los tags ajenos.
A97: Cadena de datos | B97: fuente | C97: id | D97: bigint | E97: no | F97: sí | H97: único con (id, gateway_id, campo_id) | J97: Consecutivo interno. | K97: 1
A98: Cadena de datos | B98: fuente | C98: gateway_id | D98: text | E98: no | G98: gateway.id | H98: único con (gateway_id, protocolo, endpoint) · único con (id, gateway_id, campo_id) | J98: Gateway que la lee. | K98: EPIC-CEIBA-02
A99: Cadena de datos | B99: fuente | C99: campo_id | D99: text | E99: no | G99: gateway.campo_id | H99: único con (id, gateway_id, campo_id) | J99: Campo del gateway (FK compuesta: no puede ser otro). | K99: ceiba
A100: Cadena de datos | B100: fuente | C100: protocolo | D100: text | E100: no | H100: único con (gateway_id, protocolo, endpoint) | I100: CHECK ((protocolo = ANY (ARRAY['pi-web-api'::text, 'opc-ua'::text, 'modbus-tcp'::text, 'roc-plus'::text, 'atg'::text, 'laboratorio'::text, 'ruta-manual'::text, 'sis'::text, 'calculado'::text]))) | J100: pi-web-api, opc-ua, modbus-tcp, roc-plus, atg, laboratorio, ruta-manual, sis o calculado. | K100: opc-ua
...

Sheet Relaciones
A1: Tabla | B1: Columna | C1: Apunta a la tabla | D1: Columna | E1: Cardinalidad | F1: Qué significa
A2: activo | B2: campo_id | C2: campo | D2: id | E2: N:1 | F2: Campo del activo.
A3: equipo | B3: campo_id, codigo, clase | C3: activo | D3: campo_id, codigo, clase | E3: 1:1 | F3: Campo.
A4: planta_campo | B4: campo_id | C4: campo | D4: id | E4: 1:1 | F4: Campo.
A5: planta_elemento | B5: campo_id, equipo | C5: activo | D5: campo_id, codigo | E5: N:1 | F5: Campo.
A6: planta_elemento | B6: campo_id | C6: planta_campo | D6: campo_id | E6: N:1 | F6: Campo.
A7: planta_miembro | B7: campo_id, elemento_id | C7: planta_elemento | D7: campo_id, id | E7: N:1 | F7: Campo.
A8: planta_miembro | B8: campo_id, equipo | C8: activo | D8: campo_id, codigo | E8: N:1 | F8: Campo.
A9: gateway | B9: campo_id | C9: campo | D9: id | E9: N:1 | F9: Campo donde se inscribió. Los tags que publica son de este campo (FK compuesta en fuente/dispositivo/tag).
A10: inscripcion | B10: campo_id | C10: campo | D10: id | E10: N:1 | F10: Campo para el que se emitió: el gateway que lo canjea queda de este campo.
A11: inscripcion | B11: emitido_por | C11: usuario | D11: id | E11: N:1 | F11: Id de la persona que lo pidió (del token; capacidad conector:configurar).
A12: inscripcion | B12: gateway_id | C12: gateway | D12: id | E12: N:1 | F12: Gateway que lo canjeó.
... A145: recalculo_mes | B145: campo_id | C145: campo | D145: id | E145: N:1 | F145: Campo.

Sheet Filas de ejemplo
A1: campo
A2: id | B2: nombre | C2: cuenca | D2: choke | E2: nota
A3: ceiba | B3: La Ceiba | C3: Llanos | D3: Planta | E3: Tres bombas de agua en paralelo, sin reserva: si para una, se cierran pozos.
A4: guacamayo | B4: Guacamayo | C4: Putumayo | D4: Evacuación | E4: La reinyección es para recobro: el agua tiene salida alterna.
A5: morichal | B5: Morichal Norte | C5: Llanos | D5: Pozos | E5: Todos sus pozos con electrosumergible; la reinyección tiene respaldo parcial.
A6: palmar | B6: El Palmar | C6: Magdalena Medio | D6: Planta | E6: Campo chico de bombeo mecánico.
A7: zarza | B7: La Zarza | C7: Llanos | D7: Mercado | E7: Gas con condensado: lo limita la nominación del comprador.
A9: activo
A10: campo_id | B10: codigo | C10: clase
A11: ceiba | B11: C-401 | C11: catalogo
A12: ceiba | B12: H-302 | C12: catalogo
A13: ceiba | B13: K-101 | C13: catalogo
A14: ceiba | B14: LACT-01 | C14: catalogo
A15: ceiba | B15: P-201B | C15: catalogo
A17: equipo
A18: campo_id | B18: codigo | C18: clase | D18: nombre | E18: sistema | F18: clase_iso | G18: criticidad | H18: servicio | I18: modo_falla | J18: norma | K18: intervencion_ubicacion | L18: intervencion_accion | M18: intervencion_avisar_a | N18: distribucion_falla | O18: aguas_abajo | P18: redundancia
A19: ceiba | B19: C-401 | C19: catalogo | D19: Compresor de gas | E19: Compresión | F19: compresor-gas | G19: 4 | H19: compresion | I19: Válvulas de succión y descarga ≈ 50,7 % | J19: El modo de falla #1 de la familia NO es monitoreable a nuestra resolución: se diagnostica por ángulo de cigüeñal. | K19: Batería 1 · tren de gas | L19: Ante parada súbita, verificar presión de descarga y temperatura por etapa antes de reponer: el modo dominante no avisa. | M19: Supervisor de operaciones | N19: {"fuente": "21 compresores de pistón a lo largo de 20 años. Succión y descarga suman 50,7 %: es el modo de falla #1 de la familia.", "reparto": [["Válvulas de succión", 29.1], ["Válvulas de descarga", 21.6], ["Resto de elementos", 49.3]]} | O19: tren de gas | P19: sin respaldo
A20: ceiba | B20: H-302 | C20: catalogo | D20: Tratador térmico | E20: Tratamiento de crudo | F20: tratador-termico | G20: 4 | H20: tratamiento | I20: Escama y impingimiento de llama | J20: Variable: temperatura de piel de tubo. Intervalo P-F: varía ampliamente. | K20: Batería 1 · tren de crudo | L20: No requiere intervención inmediata: H-301 toma la carga. Programar la limpieza del tubo de fuego en la próxima ventana. | M20: Planeación de mantenimiento | O20: sin impacto | P20: respaldo en línea (H-301)
A21: ceiba | B21: K-101 | C21: catalogo | D21: Sistema de aire de instrumentos | E21: Servicios industriales | F21: compresor-aire | G21: 5 | H21: aire | I21: Pérdida de suministro → válvulas a posición segura | J21: ISA-7.0.01 · API RP 14J §3.3.16. «El diseño a prueba de fallo no elimina la necesidad de supervivencia de la utilidad.» | K21: Batería 1 · servicios industriales | L21: Verificar que las tres unidades estén en servicio: hoy hay dos. Con el recibidor en 11 min de autonomía, una parada deja las válvulas en posición segura. | M21: Supervisor de operaciones | O21: todo el campo | P21: 3 unidades (N+1)
A22: ceiba | B22: LACT-01 | C22: catalogo | D22: Unidad LACT · punto de medición oficial | E22: Medición fiscal | F22: unidad-lact | G22: 5 | H22: evacuacion | I22: Deriva del factor de medidor | J22: El archivo EFM (horarios, diarios, eventos) exige ROC Plus o Totalflow, no Modbus plano. | O22: todo el campo | P22: sin respaldo
A23: ceiba | B23: P-201B | C23: catalogo | D23: Bomba multietapa de transferencia de agua | E23: Tratamiento de agua | F23: bomba-centrifuga | G23: 5 | I23: Lubricación de cojinete | J23: Centrífuga multietapa · API 610, Tabla 8: vibración en la caja de rodamientos. | K23: Batería 1 · tren de agua | L23: Llevar P-201A y P-201C a su caudal máximo y confirmar el nivel del tanque de agua antes de intentar el arranque: si ya está alto, cerrar primero los pozos con menos crudo por barril de agua. | M23: Supervisor de operaciones e ingeniería de producción | N23: {"fuente": "Reparto de bombeo en campo Sirte (Libia), 673 elementos de falla clasificados.", "reparto": [["Mecánicas", 44.1], ["Eléctricas", 27.7], ["Operacionales y de sistema", 25.4], ["Diseño", 2.4]]}
A25: planta_campo
A26: campo_id | B26: crudo_bpd | C26: crudo_cap_bpd | D26: agua_bpd | E26: agua_cap_bpd | F26: gas_bpd | G26: gas_cap_bpd | H26: choke_pozos | I26: choke_planta | J26: choke_evacuacion | K26: choke_mercado | L26: nota
A27: ceiba | B27: 10450 | C27: 12000 | D27: 224200 | E27: 267750 | F27: 3850 | G27: 4200 | H27: 12500 | I27: 11800 | J27: 14000 | K27: 15000 | L27: El agua (95 % de lo que sale de los pozos) la sacan tres bombas en paralelo, P-201A, B y C, de 90.000 bbl/d de placa; el cabezal de disposición las limita a unos 89.250 cada una. Si para una, las otras dos no alcanzan: el tanque se llena en un par de horas y hay que cerrar parte de los pozos. Es el cuello de botella del campo.
A28: guacamayo | B28: 6200 | C28: 7400 | D28: 90300 | E28: 110000 | F28: 2100 | G28: 2600 | H28: 7200 | I28: 7400 | J28: 6800 | K28: 9000 | L28: Sin compresión: el gas va a consumo propio y el excedente a tea. La restricción está aguas abajo del LACT, en la nominación del oleoducto.
A29: morichal | B29: 14800 | C29: 19500 | D29: 580400 | E29: 605500 | F29: 9100 | G29: 11000 | H29: 17950 | I29: 19500 | J29: 21000 | K29: 24000 | L29: Manda el levantamiento: 41 pozos con bomba electrosumergible y 97 % de agua, que sacan siete bombas casi al tope de lo que deja el cabezal de disposición. El compresor de gas, sin respaldo, ya cerró pozos cuando paró.
A30: palmar | B30: 3100 | C30: 3600 | D30: 13180 | E30: 16000 | F30: 0 | G30: 0 | H30: 3500 | I30: 3295 | J30: 4200 | K30: 5000 | L30: Campo chico de bombeo mecánico, sin tren de gas, con holgura en crudo y agua (80 % de agua, que saca una sola bomba de 16.000 bbl/d).
A31: zarza | B31: 2900 | C31: 3400 | D31: 1450 | E31: 4000 | F31: 12400 | G31: 16800 | H31: 3900 | I31: 3400 | J31: 4100 | K31: 3372 | L31: Campo de gas: el producto principal sale por arriba. Su restricción típica es comercial (la nominación del comprador), no técnica.
A33: planta_elemento
A34: campo_id | B34: id | C34: tren | D34: orden | E34: simbolo | F34: etiqueta | G34: equipo | H34: pie | I34: nivel_tag | J34: nivel_tope | K34: fluido | L34: pmo | M34: rama | N34: restantes_cuantos | O34: restantes_etiqueta
A35: ceiba | B35: aire | C35: servicios | D35: 1 | E35: aire | F35: Aire de instrumentos | G35: K-101 | M35: FALSE
A36: ceiba | B36: bomba | C36: agua | D36: 1 | E36: bomba | F36: Bombas de agua | G36: P-201B | M36: FALSE
A37: ceiba | B37: compresor | C37: gas | D37: 2 | E37: compresor | F37: Compresor de gas | G37: C-401 | M37: FALSE
A38: ceiba | B38: depurador | C38: gas | D38: 0 | E38: depurador | F38: Depurador de gas | H38: proceso | M38: FALSE
A39: ceiba | B39: gasventa | C39: gas | D39: 3 | E39: salida | F39: Gas a venta | H39: límite de batería | M39: FALSE
A41: planta_miembro
A42: campo_id | B42: elemento_id | C42: id | D42: orden | E42: etiqueta | F42: equipo | G42: pie | H42: nivel_tag | I42: nivel_tope | J42: fluido | K42: pmo
A43: ceiba | B43: pozos | C43: LC-09 | D43: 1 | E43: LC-09 · ESP | F43: LC-09
A44: ceiba | B44: pozos | C44: LC-14 | D44: 0 | E44: LC-14 · ESP | F44: LC-14
A45: ceiba | B45: pozos | C45: LC-21 | D45: 2 | E45: LC-21 · bombeo mecánico | F45: LC-21
A46: ceiba | B46: bomba | C46: P-201A | D46: 0 | E46: P-201A
A47: ceiba | B47: bomba | C47: P-201B | D47: 1 | E47: P-201B | F47: P-201B
A49: gateway
A50: id | B50: campo_id | C50: modelo | D50: serie | E50: firmware | F50: enlace | G50: buffer_h | H50: certificado_huella | I50: primer_visto | J50: ultimo_visto
A51: EPIC-CEIBA-01 | B51: ceiba | C51: GRV-EPIC-PR1 | D51: GRVCEI0016 | E51: 3.6.2 | F51: starlink | G51: 48 | I51: 2026-10-02T19:00:00+00:00 | J51: 2026-10-02T19:00:00+00:00
A52: EPIC-CEIBA-02 | B52: ceiba | C52: GRV-EPIC-PR1 | D52: GRVCEI9003 | E52: 3.6.0 | F52: starlink | G52: 48 | I52: 2026-10-02T19:00:00+00:00 | J52: 2026-10-02T19:00:00+00:00
A53: EPIC-GUACAMAYO-01 | B53: guacamayo | C53: GRV-EPIC-PR1 | D53: GRVGUA0015 | E53: 3.6.2 | F53: starlink | G53: 48 | I53: 2026-10-02T19:00:00+00:00 | J53: 2026-10-02T19:00:00+00:00
A54: EPIC-GUACAMAYO-02 | B54: guacamayo | C54: GRV-EPIC-PR1 | D54: GRVGUA9003 | E54: 3.6.0 | F54: starlink | G54: 48 | I54: 2026-10-02T19:00:00+00:00 | J54: 2026-10-02T19:00:00+00:00
A55: EPIC-MORICHAL-01 | B55: morichal | C55: GRV-EPIC-PR1 | D55: GRVMOR0017 | E55: 3.6.2 | F55: starlink | G55: 48 | I55: 2026-10-02T19:00:00+00:00 | J55: 2026-10-02T19:00:00+00:00
A57: nacimiento
A58: id | B58: gateway_id | C58: campo_id | D58: recibido | E58: bd_seq | F58: tags | G58: pendientes | H58: carga
A59: 1 | B59: EPIC-CEIBA-02 | C59: ceiba | D59: 2026-10-02T19:00:00+00:00 | F59: 3 | G59: 3 | H59: {"campo": "ceiba", "gateway": {"id": "EPIC-CEIBA-02", "serie": "GRVCEI9003", "enlace": "starlink", "modelo": "GRV-EPIC-PR1", "bufferH": 48, "firmware": "3.6.0"}, "dispositivos": [{"fuente": {"reloj": "el PLC del skid", "endpoint": "opc.tcp://skid-ceiba.ot.local:4840", "protocolo": "opc-ua"}, "nombre": "SKID-AMPLIACION", "metricas": [{"alto": 65, "bajo": 35, "tipo": "Nivel de interfase", "clase": "continua", "limite": "35 – 65", "nombre": "XI-1017", "unidad": "%", "cadenciaS": 5}, {"alto": 8, "bajo": null, "tipo": "Presión diferencial", "clase": "continua", "limite": "< 8", "nombre": "XT-1017", "unidad": "psi", "cadenciaS": 5}, {"alto": 1250, "bajo": 1050, "tipo": "Presión de descarga", "clase": "continua", "limite": "1.050 – 1.250", "nombre": "XP-4016", "unidad": "psi", "cadenciaS": 5}]}]}
A60: 2 | B60: EPIC-CEIBA-01 | C60: ceiba | D60: 2026-10-02T19:00:00+00:00 | F60: 30 | G60: 0 | H60: {"campo":"ceiba","gateway":{"id":"EPIC-CEIBA-01","serie":"GRVCEI0016","enlace":"starlink","modelo":"GRV-EPIC-PR1","bufferH":48,"firmware":"3.6.2"},"dispositivos":[{"fuente":{"reloj":"el PLC de la batería","endpoint":"https://pi.ceiba.local/piwebapi","protocolo":"pi-web-api"},"nombre":"V-101","metricas":[{"alto":65,"bajo":35,"tipo":"Nivel de interfase","clase":"continua","limite":"35 – 65","nombre":"LI-1012","unidad":"%","cadenciaS":47},{"alto":8,"bajo":null,"tipo":"Presión diferencial","clase":"continua","limite":"< 8","nombre":"PDI-1012","unidad":"psi","cadenciaS":47}]},{"fuente":{"reloj":"el PLC de la batería","endpoint":"https://pi.ceiba.local/piwebapi","protocolo":"pi-web-api"},"nombre":"C-401","metricas":[{"alto":1250,"bajo":1050,"tipo":"Presión de descarga","clase":"continua","limite":"1.050 – 1.250","nombre":"PI-4011","unidad":"psi","cadenciaS":47},{"alto":120,"bajo":null,"tipo":"Temperatura de descarga","clase":"continua","limite":"< 120","nombre":"TI-4011","unidad":"°C","cadenciaS":47}]},{"fuente":{"reloj":"el PLC de la batería","endpoint":"https://pi.ceiba.local/piwebapi","protocolo":"pi-web-api"},"nombre":"H-302","metricas":[{"alto":310,"bajo":280,"tipo":"Temperatura de piel de tubo","clase":"continua","limite":"280 – 310","nombre":"TI-3021","unidad":"°C","cadenciaS":47},{"alto":450,"bajo":null,"tipo":"Temperatura de chimenea","clase":"continua","limite":"< 450","nombre":"TI-3022","unidad":"°C","cadenciaS":47},{"alto":52,"bajo":38,"tipo":"Consumo de gas combustible… [recortado para el Excel: 7247 caracteres]
A61: 3 | B61: EPIC-MORICHAL-02 | C61: morichal | D61: 2026-10-02T19:00:00+00:00 | F61: 3 | G61: 3 | H61: {"campo": "morichal", "gateway": {"id": "EPIC-MORICHAL-02", "serie": "GRVMOR9003", "enlace": "starlink", "modelo": "GRV-EPIC-PR1", "bufferH": 48, "firmware": "3.6.0"}, "dispositivos": [{"fuente": {"reloj": "el PLC del skid", "endpoint": "opc.tcp://skid-morichal.ot.local:4840", "protocolo": "opc-ua"}, "nombre": "SKID-AMPLIACION", "metricas": [{"alto": 60, "bajo": 35, "tipo": "Presión de succión", "clase": "continua", "limite": "35 – 60", "nombre": "XI-3016", "unidad": "psi", "cadenciaS": 5}, {"alto": 75, "bajo": 45, "tipo": "Temperatura de succión", "clase": "continua", "limite": "45 – 75", "nombre": "XT-3016", "unidad": "°C", "cadenciaS": 5}, {"alto": 8, "bajo": null, "tipo": "Caída de presión del filtro", "clase": "continua", "limite": "< 8", "nombre": "XP-3016", "unidad": "psi", "cadenciaS": 5}]}]}
A62: 4 | B62: EPIC-MORICHAL-01 | C62: morichal | D62: 2026-10-02T19:00:00+00:00 | F62: 46 | G62: 0 | H62: {"campo":"morichal","gateway":{"id":"EPIC-MORICHAL-01","serie":"GRVMOR0017","enlace":"starlink","modelo":"GRV-EPIC-PR1","bufferH":48,"firmware":"3.6.2"},"dispositivos":[{"fuente":{"reloj":"el PLC de la batería","endpoint":"plc-morichal.ot.local:502","protocolo":"modbus-tcp"},"nombre":"MPP-301","metricas":[{"alto":60,"bajo":35,"tipo":"Presión de succión","clase":"continua","limite":"35 – 60","nombre":"PT-3011","unidad":"psi","cadenciaS":1},{"alto":75,"bajo":45,"tipo":"Temperatura de succión","clase":"continua","limite":"45 – 75","nombre":"TE-3011","unidad":"°C","cadenciaS":1},{"alto":8,"bajo":null,"tipo":"Caída de presión del filtro","clase":"continua","limite":"< 8","nombre":"PDT-3011","unidad":"psi","cadenciaS":1},{"alto":360,"bajo":320,"tipo":"Presión de descarga","clase":"continua","limite":"320 – 360","nombre":"PT-3012","unidad":"psi","cadenciaS":1},{"alto":90,"bajo":null,"tipo":"Temperatura de descarga","clase":"continua","limite":"< 90","nombre":"TE-3012","unidad":"°C","cadenciaS":1},{"alto":85,"bajo":null,"tipo":"Temperatura de rodamiento","clase":"continua","limite":"< 85","nombre":"TE-3013","unidad":"°C","cadenciaS":1},{"alto":5.5,"bajo":null,"tipo":"Vibración de la bomba","clase":"continua","limite":"< 5,5","nombre":"VT-3013","unidad":"mm/s","cadenciaS":1},{"alto":130,"bajo":null,"tipo":"Temperatura de devanado","clase":"continua","limite":"< 130","nombre":"TE-3014","unidad":"°C","cadenciaS":1},{"alto":85,"bajo":null,"tipo":"Temperatura de rodamiento del motor","cla… [recortado para el Excel: 9670 caracteres]
A63: 5 | B63: EPIC-GUACAMAYO-02 | C63: guacamayo | D63: 2026-10-02T19:00:00+00:00 | F63: 3 | G63: 3 | H63: {"campo": "guacamayo", "gateway": {"id": "EPIC-GUACAMAYO-02", "serie": "GRVGUA9003", "enlace": "starlink", "modelo": "GRV-EPIC-PR1", "bufferH": 48, "firmware": "3.6.0"}, "dispositivos": [{"fuente": {"reloj": "el PLC del skid", "endpoint": "opc.tcp://skid-guacamayo.ot.local:4840", "protocolo": "opc-ua"}, "nombre": "SKID-AMPLIACION", "metricas": [{"alto": 65, "bajo": 35, "tipo": "Nivel de interfase", "clase": "continua", "limite": "35 – 65", "nombre": "XI-1017", "unidad": "%", "cadenciaS": 5}, {"alto": 8, "bajo": null, "tipo": "Presión diferencial", "clase": "continua", "limite": "< 8", "nombre": "XT-1017", "unidad": "psi", "cadenciaS": 5}, {"alto": 310, "bajo": 280, "tipo": "Temperatura de piel de tubo", "clase": "continua", "limite": "280 – 310", "nombre": "XP-3026", "unidad": "°C", "cadenciaS": 5}]}]}
A65: fuente
A66: id | B66: gateway_id | C66: campo_id | D66: protocolo | E66: endpoint | F66: modo
A67: 1 | B67: EPIC-CEIBA-02 | C67: ceiba | D67: opc-ua | E67: opc.tcp://skid-ceiba.ot.local:4840 | F67: solo-lectura
A68: 2 | B68: EPIC-CEIBA-01 | C68: ceiba | D68: pi-web-api | E68: https://pi.ceiba.local/piwebapi | F68: solo-lectura
A69: 3 | B69: EPIC-CEIBA-01 | C69: ceiba | D69: laboratorio | F69: solo-lectura
A70: 4 | B70: EPIC-CEIBA-01 | C70: ceiba | D70: atg | E70: atg-ceiba.ot.local:10001 | F70: solo-lectura
A71: 5 | B71: EPIC-CEIBA-01 | C71: ceiba | D71: sis | F71: solo-lectura
A73: dispositivo
A74: id | B74: gateway_id | C74: campo_id | D74: fuente_id | E74: nombre | F74: reloj | G74: primer_visto | H74: ultimo_visto | I74: en_linea
A75: 1 | B75: EPIC-CEIBA-02 | C75: ceiba | D75: 1 | E75: SKID-AMPLIACION | F75: el PLC del skid | G75: 2026-10-02T19:00:00+00:00 | H75: 2026-10-02T19:00:00+00:00 | I75: TRUE
A76: 2 | B76: EPIC-CEIBA-01 | C76: ceiba | D76: 2 | E76: V-101 | F76: el PLC de la batería | G76: 2026-10-02T19:00:00+00:00 | H76: 2026-10-02T19:00:00+00:00 | I76: TRUE
A77: 3 | B77: EPIC-CEIBA-01 | C77: ceiba | D77: 2 | E77: C-401 | F77: el PLC de la batería | G77: 2026-10-02T19:00:00+00:00 | H77: 2026-10-02T19:00:00+00:00 | I77: TRUE
A78: 4 | B78: EPIC-CEIBA-01 | C78: ceiba | D78: 2 | E78: H-302 | F78: el PLC de la batería | G78: 2026-10-02T19:00:00+00:00 | H78: 2026-10-02T19:00:00+00:00 | I78: TRUE
A79: 5 | B79: EPIC-CEIBA-01 | C79: ceiba | D79: 3 | E79: H-302 | F79: la hora de la toma de muestra | G79: 2026-10-02T19:00:00+00:00 | H79: 2026-10-02T19:00:00+00:00 | I79: TRUE
A81: tag
A82: id | B82: campo_id | C82: nombre | D82: dispositivo_id | E82: equipo_codigo | F82: tipo | G82: unidad | H82: limite_texto | I82: limite_bajo | J82: limite_alto | K82: cadencia_s | L82: clase | M82: origen_mapeo | N82: actualizado
A83: 16 | B83: ceiba | C83: FQI-0101 | D83: 9 | E83: LACT-01 | F83: Medidor de desplazamiento positivo | G83: BPDC | K83: 60 | L83: continua | M83: descubierto | N83: 2026-10-02T19:00:00+00:00
A84: 25 | B84: ceiba | C84: LSH-2013 | D84: 12 | E84: P-201B | F84: Fuga del sello | L84: discreta | M84: descubierto | N84: 2026-10-02T19:00:00+00:00
A85: 32 | B85: ceiba | C85: PDT-1011 | D85: 16 | E85: K-101 | F85: Derivada de presión | G85: psi/h | H85: > -0,2 | I85: -0.2 | K85: 47 | L85: continua | M85: descubierto | N85: 2026-10-02T19:00:00+00:00
A86: 24 | B86: ceiba | C86: VI-2011 | D86: 12 | E86: P-201B | F86: Vibración global | G86: mm/s | H86: < 3,9 | J86: 3.9 | K86: 47 | L86: continua | M86: descubierto | N86: 2026-10-02T19:00:00+00:00
A87: 1 | B87: ceiba | C87: XI-1017 | D87: 1 | F87: Nivel de interfase | G87: % | H87: 35 – 65 | I87: 35 | J87: 65 | K87: 5 | L87: continua | M87: pendiente | N87: 2026-10-02T19:00:00+00:00
A89: formula
A90: id | B90: version | C90: clase_equipo | D90: tipo_tag | E90: expresion | F90: ventana_min | G90: activa
A91: f1-compresor-aire | B91: 2 | C91: compresor-aire | D91: Derivada de presión | E91: pendiente de la presión de cabezal (PT-1011) en la ventana, en psi/h | F91: 15 | G91: TRUE
A93: calculo
A94: tag_id | B94: formula_id | C94: formula_version
A95: 32 | B95: f1-compresor-aire | C95: 2
A96: 81 | B96: f1-compresor-aire | C96: 2
A97: 112 | B97: f1-compresor-aire | C97: 2
A98: 143 | B98: f1-compresor-aire | C98: 2
A99: 172 | B99: f1-compresor-aire | C99: 2
A101: calculo_entrada
A102: tag_id | B102: entrada_tag_id
A103: 32 | B103: 30
A104: 81 | B104: 79
A105: 112 | B105: 110
A106: 143 | B106: 141
A107: 172 | B107: 170
A109: calibracion
A110: tag_id | B110: vigente_hasta | C110: detalle
A111: 12 | C111: Verificado contra cinta el 3 de marzo de 2026 · vigente hasta marzo de 2027
A112: 13 | C112: Verificado contra cinta el 3 de marzo de 2026 · vigente hasta marzo de 2027
A113: 16 | C113: Probado el 12 de abril de 2026 · factor 1,0021 · vigente hasta abril de 2027
A114: 17 | C114: Analizador verificado el 20 de enero de 2026 · vigente hasta enero de 2027
...

Sheet Diagrama
